{
"meta":{"test_sets":[],"test_metrics":[],"learn_metrics":[{"best_value":"Min","name":"Logloss"}],"launch_mode":"Train","parameters":"","iteration_count":1000,"learn_sets":["learn"],"name":"experiment"},
"iterations":[
{"learn":[0.6866219598],"iteration":0,"passed_time":0.001296434222,"remaining_time":1.295137788},
{"learn":[0.6800278867],"iteration":1,"passed_time":0.003829478802,"remaining_time":1.910909922},
{"learn":[0.6747549497],"iteration":2,"passed_time":0.01002699411,"remaining_time":3.332304377},
{"learn":[0.6681232917],"iteration":3,"passed_time":0.09599050143,"remaining_time":23.90163486},
{"learn":[0.662719428],"iteration":4,"passed_time":0.09846599591,"remaining_time":19.59473319},
{"learn":[0.6560065173],"iteration":5,"passed_time":0.1220155813,"remaining_time":20.21391464},
{"learn":[0.6507262823],"iteration":6,"passed_time":0.1241139703,"remaining_time":17.60645321},
{"learn":[0.645647454],"iteration":7,"passed_time":0.1260750298,"remaining_time":15.6333037},
{"learn":[0.6406306146],"iteration":8,"passed_time":0.1508728321,"remaining_time":16.61277517},
{"learn":[0.635811926],"iteration":9,"passed_time":0.1529071266,"remaining_time":15.13780553},
{"learn":[0.6312231816],"iteration":10,"passed_time":0.178844194,"remaining_time":16.07971889},
{"learn":[0.6263633783],"iteration":11,"passed_time":0.2062804001,"remaining_time":16.98375294},
{"learn":[0.6220032683],"iteration":12,"passed_time":0.2094096187,"remaining_time":15.89902259},
{"learn":[0.6171899599],"iteration":13,"passed_time":0.2582406062,"remaining_time":18.18751698},
{"learn":[0.6127851175],"iteration":14,"passed_time":0.2607384263,"remaining_time":17.12182333},
{"learn":[0.6084493374],"iteration":15,"passed_time":0.2631503117,"remaining_time":16.18374417},
{"learn":[0.603302538],"iteration":16,"passed_time":0.3061467561,"remaining_time":17.70248595},
{"learn":[0.5992658367],"iteration":17,"passed_time":0.3081815552,"remaining_time":16.81301596},
{"learn":[0.5953671679],"iteration":18,"passed_time":0.3209688917,"remaining_time":16.57213067},
{"learn":[0.5921029794],"iteration":19,"passed_time":0.3245259153,"remaining_time":15.90176985},
{"learn":[0.5883775751],"iteration":20,"passed_time":0.3559878137,"remaining_time":16.59581284},
{"learn":[0.5849356527],"iteration":21,"passed_time":0.3579527843,"remaining_time":15.91262832},
{"learn":[0.5813822097],"iteration":22,"passed_time":0.3599899274,"remaining_time":15.29174605},
{"learn":[0.5776389882],"iteration":23,"passed_time":0.3613103392,"remaining_time":14.69328713},
{"learn":[0.5732074971],"iteration":24,"passed_time":0.3623818728,"remaining_time":14.13289304},
{"learn":[0.5701982512],"iteration":25,"passed_time":0.3638586937,"remaining_time":13.63070645},
{"learn":[0.567231821],"iteration":26,"passed_time":0.3653550287,"remaining_time":13.1663127},
{"learn":[0.5640311385],"iteration":27,"passed_time":0.3665023974,"remaining_time":12.72286894},
{"learn":[0.5603515871],"iteration":28,"passed_time":0.367686266,"remaining_time":12.31115049},
{"learn":[0.5567644279],"iteration":29,"passed_time":0.3688883509,"remaining_time":11.92739001},
{"learn":[0.5538353224],"iteration":30,"passed_time":0.3709279838,"remaining_time":11.59449085},
{"learn":[0.550434253],"iteration":31,"passed_time":0.3726410247,"remaining_time":11.272391},
{"learn":[0.5476686304],"iteration":32,"passed_time":0.3738062426,"remaining_time":10.95365565},
{"learn":[0.5449237861],"iteration":33,"passed_time":0.3749581257,"remaining_time":10.65322204},
{"learn":[0.5413594383],"iteration":34,"passed_time":0.3760970768,"remaining_time":10.36953369},
{"learn":[0.5380922443],"iteration":35,"passed_time":0.3772102735,"remaining_time":10.10085288},
{"learn":[0.5357456042],"iteration":36,"passed_time":0.3784479702,"remaining_time":9.849875548},
{"learn":[0.5333268504],"iteration":37,"passed_time":0.3796621067,"remaining_time":9.611445965},
{"learn":[0.5309857972],"iteration":38,"passed_time":0.3808550642,"remaining_time":9.384659402},
{"learn":[0.528740164],"iteration":39,"passed_time":0.3820621048,"remaining_time":9.169490515},
{"learn":[0.5263910617],"iteration":40,"passed_time":0.3832596098,"remaining_time":8.964535751},
{"learn":[0.5235581324],"iteration":41,"passed_time":0.3853655846,"remaining_time":8.790005478},
{"learn":[0.5209928781],"iteration":42,"passed_time":0.3873939429,"remaining_time":8.621767519},
{"learn":[0.5187406753],"iteration":43,"passed_time":0.388601397,"remaining_time":8.443248535},
{"learn":[0.5166419684],"iteration":44,"passed_time":0.3897313958,"remaining_time":8.270966289},
{"learn":[0.5144666364],"iteration":45,"passed_time":0.3909753567,"remaining_time":8.10848892},
{"learn":[0.5121670778],"iteration":46,"passed_time":0.3926070367,"remaining_time":7.96073417},
{"learn":[0.5093338633],"iteration":47,"passed_time":0.3938184451,"remaining_time":7.810732494},
{"learn":[0.5072269613],"iteration":48,"passed_time":0.3949720541,"remaining_time":7.665682112},
{"learn":[0.5052282252],"iteration":49,"passed_time":0.3961445215,"remaining_time":7.526745908},
{"learn":[0.5033423359],"iteration":50,"passed_time":0.3973210719,"remaining_time":7.39328818},
{"learn":[0.5012065096],"iteration":51,"passed_time":0.3984103033,"remaining_time":7.2633263},
{"learn":[0.4993009937],"iteration":52,"passed_time":0.4124539904,"remaining_time":7.369696772},
{"learn":[0.4973320762],"iteration":53,"passed_time":0.4136893948,"remaining_time":7.247225324},
{"learn":[0.4954507595],"iteration":54,"passed_time":0.4148680886,"remaining_time":7.128188067},
{"learn":[0.4928461344],"iteration":55,"passed_time":0.416986345,"remaining_time":7.029198387},
{"learn":[0.4911227523],"iteration":56,"passed_time":0.4190375558,"remaining_time":6.932498512},
{"learn":[0.4890303801],"iteration":57,"passed_time":0.4201551319,"remaining_time":6.823898866},
{"learn":[0.4873119683],"iteration":58,"passed_time":0.4213555579,"remaining_time":6.720264068},
{"learn":[0.4857560342],"iteration":59,"passed_time":0.4224887023,"remaining_time":6.61898967},
{"learn":[0.4844935347],"iteration":60,"passed_time":0.4237894912,"remaining_time":6.523579217},
{"learn":[0.4829212728],"iteration":61,"passed_time":0.4248998941,"remaining_time":6.428324204},
{"learn":[0.4814488566],"iteration":62,"passed_time":0.4260090301,"remaining_time":6.336039067},
{"learn":[0.4799811441],"iteration":63,"passed_time":0.4408244556,"remaining_time":6.447057662},
{"learn":[0.478715738],"iteration":64,"passed_time":0.4433445658,"remaining_time":6.377341062},
{"learn":[0.4772786376],"iteration":65,"passed_time":0.445541992,"remaining_time":6.305094251},
{"learn":[0.4755413456],"iteration":66,"passed_time":0.4470871586,"remaining_time":6.225855507},
{"learn":[0.4741084615],"iteration":67,"passed_time":0.4482525492,"remaining_time":6.143696704},
{"learn":[0.4727702163],"iteration":68,"passed_time":0.4494394415,"remaining_time":6.064175653},
{"learn":[0.4713177933],"iteration":69,"passed_time":0.4507371712,"remaining_time":5.988365274},
{"learn":[0.4699026455],"iteration":70,"passed_time":0.4519146389,"remaining_time":5.913080276},
{"learn":[0.4685086825],"iteration":71,"passed_time":0.4532432469,"remaining_time":5.841801849},
{"learn":[0.4671427744],"iteration":72,"passed_time":0.4543847927,"remaining_time":5.770064423},
{"learn":[0.4659506225],"iteration":73,"passed_time":0.455532477,"remaining_time":5.700311807},
{"learn":[0.4646590714],"iteration":74,"passed_time":0.4566938232,"remaining_time":5.632557153},
{"learn":[0.4633488054],"iteration":75,"passed_time":0.4578251769,"remaining_time":5.566190308},
{"learn":[0.4619371074],"iteration":76,"passed_time":0.459028075,"remaining_time":5.502375496},
{"learn":[0.4609254701],"iteration":77,"passed_time":0.460275261,"remaining_time":5.440689624},
{"learn":[0.4598382558],"iteration":78,"passed_time":0.4614854928,"remaining_time":5.380103023},
{"learn":[0.4587127137],"iteration":79,"passed_time":0.46272744,"remaining_time":5.32136556},
{"learn":[0.4576062426],"iteration":80,"passed_time":0.4638653665,"remaining_time":5.262867553},
{"learn":[0.4563134998],"iteration":81,"passed_time":0.4650932783,"remaining_time":5.20677597},
{"learn":[0.4554776185],"iteration":82,"passed_time":0.467077854,"remaining_time":5.16036617},
{"learn":[0.454534695],"iteration":83,"passed_time":0.4684179442,"remaining_time":5.107986154},
{"learn":[0.4532069062],"iteration":84,"passed_time":0.4695202335,"remaining_time":5.054247219},
{"learn":[0.4522289425],"iteration":85,"passed_time":0.4706398533,"remaining_time":5.001916581},
{"learn":[0.4515068242],"iteration":86,"passed_time":0.471841912,"remaining_time":4.951628341},
{"learn":[0.4504739504],"iteration":87,"passed_time":0.4729786179,"remaining_time":4.901778404},
{"learn":[0.4494001208],"iteration":88,"passed_time":0.4742655798,"remaining_time":4.854561159},
{"learn":[0.4477734966],"iteration":89,"passed_time":0.4754710248,"remaining_time":4.807540362},
{"learn":[0.4465243654],"iteration":90,"passed_time":0.4770333715,"remaining_time":4.76509159},
{"learn":[0.4454578126],"iteration":91,"passed_time":0.4784270576,"remaining_time":4.721867047},
{"learn":[0.444549014],"iteration":92,"passed_time":0.4805321946,"remaining_time":4.68648065},
{"learn":[0.443640116],"iteration":93,"passed_time":0.4818263913,"remaining_time":4.643986282},
{"learn":[0.4428914198],"iteration":94,"passed_time":0.4829913028,"remaining_time":4.601127674},
{"learn":[0.4418491379],"iteration":95,"passed_time":0.4842218488,"remaining_time":4.559755743},
{"learn":[0.4411402705],"iteration":96,"passed_time":0.4855118467,"remaining_time":4.519764923},
{"learn":[0.4404816747],"iteration":97,"passed_time":0.4867275102,"remaining_time":4.479879737},
{"learn":[0.4395376129],"iteration":98,"passed_time":0.4878725704,"remaining_time":4.440133192},
{"learn":[0.4386685425],"iteration":99,"passed_time":0.4891294379,"remaining_time":4.402164941},
{"learn":[0.4375162651],"iteration":100,"passed_time":0.4910161838,"remaining_time":4.370530191},
{"learn":[0.4363886405],"iteration":101,"passed_time":0.4925083193,"remaining_time":4.336004615},
{"learn":[0.4356576868],"iteration":102,"passed_time":0.4937979129,"remaining_time":4.300356581},
{"learn":[0.4348435879],"iteration":103,"passed_time":0.494920538,"remaining_time":4.263930789},
{"learn":[0.4340074261],"iteration":104,"passed_time":0.4961654487,"remaining_time":4.229219777},
{"learn":[0.433133688],"iteration":105,"passed_time":0.4981877996,"remaining_time":4.201697102},
{"learn":[0.4325173771],"iteration":106,"passed_time":0.5002373192,"remaining_time":4.174877813},
{"learn":[0.4315233034],"iteration":107,"passed_time":0.5014850121,"remaining_time":4.14189473},
{"learn":[0.4306927397],"iteration":108,"passed_time":0.5026728958,"remaining_time":4.109005048},
{"learn":[0.4298361829],"iteration":109,"passed_time":0.5038123392,"remaining_time":4.076299835},
{"learn":[0.4289734159],"iteration":110,"passed_time":0.5050238239,"remaining_time":4.044740356},
{"learn":[0.4284167172],"iteration":111,"passed_time":0.5062809707,"remaining_time":4.014084839},
{"learn":[0.4276923541],"iteration":112,"passed_time":0.5074414358,"remaining_time":3.983190739},
{"learn":[0.4270757773],"iteration":113,"passed_time":0.5085845108,"remaining_time":3.952683128},
{"learn":[0.4264965021],"iteration":114,"passed_time":0.5097819734,"remaining_time":3.923104752},
{"learn":[0.4259076104],"iteration":115,"passed_time":0.5112298711,"remaining_time":3.89592419},
{"learn":[0.4252638782],"iteration":116,"passed_time":0.5125639239,"remaining_time":3.868324315},
{"learn":[0.4243856961],"iteration":117,"passed_time":0.5136794692,"remaining_time":3.839536371},
{"learn":[0.4236889575],"iteration":118,"passed_time":0.5147644625,"remaining_time":3.810987323},
{"learn":[0.4230495075],"iteration":119,"passed_time":0.5161394447,"remaining_time":3.785022594},
{"learn":[0.4226599673],"iteration":120,"passed_time":0.5172151038,"remaining_time":3.757289886},
{"learn":[0.4219998802],"iteration":121,"passed_time":0.5183509879,"remaining_time":3.730427602},
{"learn":[0.4214493645],"iteration":122,"passed_time":0.5194572954,"remaining_time":3.703772749},
{"learn":[0.4209278968],"iteration":123,"passed_time":0.5207051249,"remaining_time":3.678529754},
{"learn":[0.4199987893],"iteration":124,"passed_time":0.5223050918,"remaining_time":3.656135642},
{"learn":[0.4192829859],"iteration":125,"passed_time":0.5238791298,"remaining_time":3.633891742},
{"learn":[0.4187416237],"iteration":126,"passed_time":0.5249597076,"remaining_time":3.608581297},
{"learn":[0.4181376838],"iteration":127,"passed_time":0.5261229656,"remaining_time":3.584212703},
{"learn":[0.4176057498],"iteration":128,"passed_time":0.5272540832,"remaining_time":3.559986872},
{"learn":[0.4171662848],"iteration":129,"passed_time":0.5283958759,"remaining_time":3.536187785},
{"learn":[0.4162577458],"iteration":130,"passed_time":0.5297799276,"remaining_time":3.514341657},
{"learn":[0.4156723611],"iteration":131,"passed_time":0.5311747741,"remaining_time":3.492876545},
{"learn":[0.4150868594],"iteration":132,"passed_time":0.5323523291,"remaining_time":3.470296762},
{"learn":[0.4146082278],"iteration":133,"passed_time":0.5334590579,"remaining_time":3.447578687},
{"learn":[0.4142292813],"iteration":134,"passed_time":0.53495878,"remaining_time":3.427698849},
{"learn":[0.4136234758],"iteration":135,"passed_time":0.5361892688,"remaining_time":3.406378884},
{"learn":[0.4129880234],"iteration":136,"passed_time":0.5376432749,"remaining_time":3.386760191},
{"learn":[0.412606983],"iteration":137,"passed_time":0.5394390772,"remaining_time":3.369539743},
{"learn":[0.4120030708],"iteration":138,"passed_time":0.5405043566,"remaining_time":3.348016194},
{"learn":[0.4113727778],"iteration":139,"passed_time":0.5415969729,"remaining_time":3.326952833},
{"learn":[0.4107898806],"iteration":140,"passed_time":0.5427851891,"remaining_time":3.306755159},
{"learn":[0.4102186079],"iteration":141,"passed_time":0.5440195034,"remaining_time":3.28710376},
{"learn":[0.4096969165],"iteration":142,"passed_time":0.5453321703,"remaining_time":3.26817951},
{"learn":[0.409395373],"iteration":143,"passed_time":0.5468534688,"remaining_time":3.250740065},
{"learn":[0.4088060065],"iteration":144,"passed_time":0.5481649746,"remaining_time":3.232283126},
{"learn":[0.4083514402],"iteration":145,"passed_time":0.5501228044,"remaining_time":3.217841609},
{"learn":[0.4078998838],"iteration":146,"passed_time":0.551689417,"remaining_time":3.201299814},
{"learn":[0.4074638784],"iteration":147,"passed_time":0.5528691987,"remaining_time":3.182733495},
{"learn":[0.4067644668],"iteration":148,"passed_time":0.5540566866,"remaining_time":3.164444566},
{"learn":[0.4062865326],"iteration":149,"passed_time":0.5553269243,"remaining_time":3.146852571},
{"learn":[0.4059316115],"iteration":150,"passed_time":0.5564339046,"remaining_time":3.128558841},
{"learn":[0.40541881],"iteration":151,"passed_time":0.5576463082,"remaining_time":3.111079404},
{"learn":[0.4050369356],"iteration":152,"passed_time":0.558870877,"remaining_time":3.093879953},
{"learn":[0.4046026485],"iteration":153,"passed_time":0.5600833972,"remaining_time":3.076821779},
{"learn":[0.4040895211],"iteration":154,"passed_time":0.5612924693,"remaining_time":3.059949268},
{"learn":[0.4034779496],"iteration":155,"passed_time":0.5624711422,"remaining_time":3.043113103},
{"learn":[0.4031373874],"iteration":156,"passed_time":0.5635698005,"remaining_time":3.026046763},
{"learn":[0.4026380497],"iteration":157,"passed_time":0.5646694819,"remaining_time":3.009187999},
{"learn":[0.4021998315],"iteration":158,"passed_time":0.5658602536,"remaining_time":2.993009266},
{"learn":[0.401673824],"iteration":159,"passed_time":0.5671307011,"remaining_time":2.977436181},
{"learn":[0.4012674107],"iteration":160,"passed_time":0.5683911062,"remaining_time":2.961988435},
{"learn":[0.4008451648],"iteration":161,"passed_time":0.5697780396,"remaining_time":2.947370353},
{"learn":[0.4003173606],"iteration":162,"passed_time":0.5709847963,"remaining_time":2.931989414},
{"learn":[0.3999635471],"iteration":163,"passed_time":0.5725418046,"remaining_time":2.91856676},
{"learn":[0.3995284541],"iteration":164,"passed_time":0.57409679,"remaining_time":2.905277695},
{"learn":[0.3990860566],"iteration":165,"passed_time":0.5753038838,"remaining_time":2.890382163},
{"learn":[0.3985760935],"iteration":166,"passed_time":0.5764180418,"remaining_time":2.875186999},
{"learn":[0.3982189246],"iteration":167,"passed_time":0.5778061759,"remaining_time":2.861516299},
{"learn":[0.3977115953],"iteration":168,"passed_time":0.5792127546,"remaining_time":2.848081651},
{"learn":[0.3970949699],"iteration":169,"passed_time":0.5806145289,"remaining_time":2.834765053},
{"learn":[0.3968032703],"iteration":170,"passed_time":0.5817221873,"remaining_time":2.820161949},
{"learn":[0.3964197904],"iteration":171,"passed_time":0.5828274895,"remaining_time":2.805704426},
{"learn":[0.3958261602],"iteration":172,"passed_time":0.5839768797,"remaining_time":2.79161202},
{"learn":[0.3955203377],"iteration":173,"passed_time":0.5852353705,"remaining_time":2.778186299},
{"learn":[0.3951620371],"iteration":174,"passed_time":0.5867169827,"remaining_time":2.76595149},
{"learn":[0.3948436737],"iteration":175,"passed_time":0.5886896588,"remaining_time":2.756137948},
{"learn":[0.394326017],"iteration":176,"passed_time":0.5903007105,"remaining_time":2.744731552},
{"learn":[0.3938907056],"iteration":177,"passed_time":0.5915614828,"remaining_time":2.731817634},
{"learn":[0.3933384944],"iteration":178,"passed_time":0.5927944622,"remaining_time":2.718906444},
{"learn":[0.3930478781],"iteration":179,"passed_time":0.5940422107,"remaining_time":2.706192293},
{"learn":[0.3926796243],"iteration":180,"passed_time":0.5951636453,"remaining_time":2.69303329},
{"learn":[0.3922350607],"iteration":181,"passed_time":0.5963389851,"remaining_time":2.680248845},
{"learn":[0.3918304962],"iteration":182,"passed_time":0.5974505091,"remaining_time":2.667306371},
{"learn":[0.3911858485],"iteration":183,"passed_time":0.5985589352,"remaining_time":2.654478756},
{"learn":[0.3907792238],"iteration":184,"passed_time":0.5997211386,"remaining_time":2.642014746},
{"learn":[0.3903780854],"iteration":185,"passed_time":0.6008852354,"remaining_time":2.629680546},
{"learn":[0.3899477772],"iteration":186,"passed_time":0.6022375894,"remaining_time":2.618284279},
{"learn":[0.3894620675],"iteration":187,"passed_time":0.603454529,"remaining_time":2.606409987},
{"learn":[0.3891985662],"iteration":188,"passed_time":0.6053564777,"remaining_time":2.597587849},
{"learn":[0.3887536162],"iteration":189,"passed_time":0.6065139229,"remaining_time":2.585664619},
{"learn":[0.3886037953],"iteration":190,"passed_time":0.6085577924,"remaining_time":2.57760866},
{"learn":[0.3883297393],"iteration":191,"passed_time":0.6100884051,"remaining_time":2.567455372},
{"learn":[0.3879491781],"iteration":192,"passed_time":0.611237185,"remaining_time":2.555794862},
{"learn":[0.3877804479],"iteration":193,"passed_time":0.6123678481,"remaining_time":2.544167451},
{"learn":[0.3870624587],"iteration":194,"passed_time":0.6134747003,"remaining_time":2.532549404},
{"learn":[0.3867509698],"iteration":195,"passed_time":0.6147152039,"remaining_time":2.521586857},
{"learn":[0.3864512219],"iteration":196,"passed_time":0.615925732,"remaining_time":2.510600826},
{"learn":[0.3859953401],"iteration":197,"passed_time":0.6172533269,"remaining_time":2.500187718},
{"learn":[0.3857351143],"iteration":198,"passed_time":0.6184852994,"remaining_time":2.489481029},
{"learn":[0.3852763239],"iteration":199,"passed_time":0.6199733873,"remaining_time":2.479893549},
{"learn":[0.3848441614],"iteration":200,"passed_time":0.6212182702,"remaining_time":2.46941989},
{"learn":[0.3844798385],"iteration":201,"passed_time":0.6223835359,"remaining_time":2.458723077},
{"learn":[0.3842000795],"iteration":202,"passed_time":0.6235687431,"remaining_time":2.448198464},
{"learn":[0.3839296041],"iteration":203,"passed_time":0.624642164,"remaining_time":2.437329228},
{"learn":[0.3835110447],"iteration":204,"passed_time":0.6257207519,"remaining_time":2.426575599},
{"learn":[0.3833412844],"iteration":205,"passed_time":0.6270730411,"remaining_time":2.416970848},
{"learn":[0.3828531835],"iteration":206,"passed_time":0.6282833492,"remaining_time":2.406901913},
{"learn":[0.3825670441],"iteration":207,"passed_time":0.6295314573,"remaining_time":2.397062087},
{"learn":[0.3822312509],"iteration":208,"passed_time":0.6308270304,"remaining_time":2.38748412},
{"learn":[0.3820831973],"iteration":209,"passed_time":0.6323331279,"remaining_time":2.378777005},
{"learn":[0.3816322844],"iteration":210,"passed_time":0.6337211122,"remaining_time":2.369696481},
{"learn":[0.3812696063],"iteration":211,"passed_time":0.6349629521,"remaining_time":2.360145313},
{"learn":[0.3808499643],"iteration":212,"passed_time":0.6364799169,"remaining_time":2.351688707},
{"learn":[0.3806591017],"iteration":213,"passed_time":0.6378933192,"remaining_time":2.342916584},
{"learn":[0.3804675016],"iteration":214,"passed_time":0.6391370603,"remaining_time":2.333593453},
{"learn":[0.3801012321],"iteration":215,"passed_time":0.6403527747,"remaining_time":2.324243404},
{"learn":[0.3798207665],"iteration":216,"passed_time":0.6416579722,"remaining_time":2.315291208},
{"learn":[0.3796547026],"iteration":217,"passed_time":0.6429060478,"remaining_time":2.306204263},
{"learn":[0.379195262],"iteration":218,"passed_time":0.6444535722,"remaining_time":2.298256803},
{"learn":[0.3787900702],"iteration":219,"passed_time":0.6457342521,"remaining_time":2.289421439},
{"learn":[0.3786204874],"iteration":220,"passed_time":0.647801978,"remaining_time":2.283428692},
{"learn":[0.3782081052],"iteration":221,"passed_time":0.650074528,"remaining_time":2.278189112},
{"learn":[0.3779378752],"iteration":222,"passed_time":0.6710555319,"remaining_time":2.3381621},
{"learn":[0.3775092984],"iteration":223,"passed_time":0.6723093602,"remaining_time":2.329071712},
{"learn":[0.3771394232],"iteration":224,"passed_time":0.6733661278,"remaining_time":2.319372218},
{"learn":[0.3767525513],"iteration":225,"passed_time":0.6744857724,"remaining_time":2.309964548},
{"learn":[0.3764243579],"iteration":226,"passed_time":0.6755902613,"remaining_time":2.300578291},
{"learn":[0.3762369257],"iteration":227,"passed_time":0.6767006357,"remaining_time":2.291284609},
{"learn":[0.3760188995],"iteration":228,"passed_time":0.6777952472,"remaining_time":2.282009326},
{"learn":[0.3758638325],"iteration":229,"passed_time":0.6789358764,"remaining_time":2.272959238},
{"learn":[0.3756528855],"iteration":230,"passed_time":0.6800519047,"remaining_time":2.263895735},
{"learn":[0.3753660506],"iteration":231,"passed_time":0.6811578658,"remaining_time":2.254867418},
{"learn":[0.3751537899],"iteration":232,"passed_time":0.6822619234,"remaining_time":2.245900838},
{"learn":[0.3748461086],"iteration":233,"passed_time":0.6834540036,"remaining_time":2.237289602},
{"learn":[0.3746738118],"iteration":234,"passed_time":0.6847081066,"remaining_time":2.228943411},
{"learn":[0.374360525],"iteration":235,"passed_time":0.6862761667,"remaining_time":2.221673692},
{"learn":[0.3739296573],"iteration":236,"passed_time":0.687448411,"remaining_time":2.213177796},
{"learn":[0.3735027366],"iteration":237,"passed_time":0.6886127138,"remaining_time":2.204718016},
{"learn":[0.3732997118],"iteration":238,"passed_time":0.6898317706,"remaining_time":2.196493629},
{"learn":[0.3731078839],"iteration":239,"passed_time":0.6910292717,"remaining_time":2.18825936},
{"learn":[0.3727404403],"iteration":240,"passed_time":0.6922348116,"remaining_time":2.180108805},
{"learn":[0.3724920313],"iteration":241,"passed_time":0.6934928542,"remaining_time":2.172180097},
{"learn":[0.3722152761],"iteration":242,"passed_time":0.6947563254,"remaining_time":2.164323203},
{"learn":[0.3720638757],"iteration":243,"passed_time":0.6961030239,"remaining_time":2.156778222},
{"learn":[0.3718995573],"iteration":244,"passed_time":0.6971549825,"remaining_time":2.148375558},
{"learn":[0.3716874614],"iteration":245,"passed_time":0.6983191001,"remaining_time":2.140376429},
{"learn":[0.3714753407],"iteration":246,"passed_time":0.6993929854,"remaining_time":2.132157563},
{"learn":[0.3712521303],"iteration":247,"passed_time":0.7005181635,"remaining_time":2.124151851},
{"learn":[0.3710867486],"iteration":248,"passed_time":0.7016397894,"remaining_time":2.11619069},
{"learn":[0.3707796768],"iteration":249,"passed_time":0.7029865327,"remaining_time":2.108959598},
{"learn":[0.3705294884],"iteration":250,"passed_time":0.7041105558,"remaining_time":2.101110782},
{"learn":[0.370420307],"iteration":251,"passed_time":0.7052996632,"remaining_time":2.093508524},
{"learn":[0.3702208234],"iteration":252,"passed_time":0.7064135127,"remaining_time":2.085734759},
{"learn":[0.3699195105],"iteration":253,"passed_time":0.7079524983,"remaining_time":2.079262062},
{"learn":[0.3696830142],"iteration":254,"passed_time":0.7094018033,"remaining_time":2.072566053},
{"learn":[0.3695178553],"iteration":255,"passed_time":0.7106603288,"remaining_time":2.065356581},
{"learn":[0.3693290622],"iteration":256,"passed_time":0.7119028647,"remaining_time":2.058147192},
{"learn":[0.3689369514],"iteration":257,"passed_time":0.7131751732,"remaining_time":2.051069684},
{"learn":[0.3687288508],"iteration":258,"passed_time":0.7144170903,"remaining_time":2.043950054},
{"learn":[0.3684608529],"iteration":259,"passed_time":0.7159886926,"remaining_time":2.037813971},
{"learn":[0.3682677382],"iteration":260,"passed_time":0.7175503565,"remaining_time":2.031684726},
{"learn":[0.3681696756],"iteration":261,"passed_time":0.7191389861,"remaining_time":2.025666304},
{"learn":[0.3678119853],"iteration":262,"passed_time":0.720251081,"remaining_time":2.018346185},
{"learn":[0.3675328957],"iteration":263,"passed_time":0.7213326849,"remaining_time":2.010988091},
{"learn":[0.367247508],"iteration":264,"passed_time":0.7224416882,"remaining_time":2.003753362},
{"learn":[0.3670803341],"iteration":265,"passed_time":0.7236886867,"remaining_time":1.996945474},
{"learn":[0.3666931578],"iteration":266,"passed_time":0.7248336945,"remaining_time":1.989899244},
{"learn":[0.3664871872],"iteration":267,"passed_time":0.7260050408,"remaining_time":1.982968992},
{"learn":[0.3662212336],"iteration":268,"passed_time":0.7271586275,"remaining_time":1.976033296},
{"learn":[0.3661042518],"iteration":269,"passed_time":0.7282636727,"remaining_time":1.969009189},
{"learn":[0.3659111942],"iteration":270,"passed_time":0.7295677854,"remaining_time":1.962564264},
{"learn":[0.3655715977],"iteration":271,"passed_time":0.7307599351,"remaining_time":1.955857473},
{"learn":[0.3652575067],"iteration":272,"passed_time":0.7324080144,"remaining_time":1.950405225},
{"learn":[0.3649903834],"iteration":273,"passed_time":0.7341569711,"remaining_time":1.945248033},
{"learn":[0.3647374473],"iteration":274,"passed_time":0.7356059134,"remaining_time":1.939324681},
{"learn":[0.3645189148],"iteration":275,"passed_time":0.7366753662,"remaining_time":1.932438279},
{"learn":[0.3644195039],"iteration":276,"passed_time":0.7498220047,"remaining_time":1.95711664},
{"learn":[0.3643207099],"iteration":277,"passed_time":0.7553378981,"remaining_time":1.961704901},
{"learn":[0.3640261772],"iteration":278,"passed_time":0.7572201197,"remaining_time":1.956830488},
{"learn":[0.3637028167],"iteration":279,"passed_time":0.7781964472,"remaining_time":2.001076578},
{"learn":[0.363586785],"iteration":280,"passed_time":0.7794114417,"remaining_time":1.994294757},
{"learn":[0.3633818691],"iteration":281,"passed_time":0.7838779891,"remaining_time":1.995831192},
{"learn":[0.3632919116],"iteration":282,"passed_time":0.8484984307,"remaining_time":2.14972924},
{"learn":[0.3630904235],"iteration":283,"passed_time":0.8690766379,"remaining_time":2.191052369},
{"learn":[0.3628395667],"iteration":284,"passed_time":0.8713045535,"remaining_time":2.185904406},
{"learn":[0.362706012],"iteration":285,"passed_time":0.9186749328,"remaining_time":2.293475182},
{"learn":[0.3624831261],"iteration":286,"passed_time":0.9223958503,"remaining_time":2.291526973},
{"learn":[0.3623280889],"iteration":287,"passed_time":0.9529540949,"remaining_time":2.35591429},
{"learn":[0.3621036442],"iteration":288,"passed_time":0.9542876285,"remaining_time":2.347745688},
{"learn":[0.361882162],"iteration":289,"passed_time":0.9740100143,"remaining_time":2.384645207},
{"learn":[0.3617917754],"iteration":290,"passed_time":0.9896371924,"remaining_time":2.411177902},
{"learn":[0.3615938284],"iteration":291,"passed_time":0.9930729457,"remaining_time":2.4078618},
{"learn":[0.3614801538],"iteration":292,"passed_time":0.9946999554,"remaining_time":2.400180438},
{"learn":[0.3612173997],"iteration":293,"passed_time":1.000681411,"remaining_time":2.402996858},
{"learn":[0.3610062353],"iteration":294,"passed_time":1.006858202,"remaining_time":2.406220449},
{"learn":[0.3608627389],"iteration":295,"passed_time":1.014639536,"remaining_time":2.413196735},
{"learn":[0.3607412508],"iteration":296,"passed_time":1.032718203,"remaining_time":2.444447463},
{"learn":[0.3606006422],"iteration":297,"passed_time":1.055079688,"remaining_time":2.485456179},
{"learn":[0.3603792928],"iteration":298,"passed_time":1.059341456,"remaining_time":2.483606557},
{"learn":[0.3601793091],"iteration":299,"passed_time":1.062059932,"remaining_time":2.478139842},
{"learn":[0.3599851744],"iteration":300,"passed_time":1.08090578,"remaining_time":2.510143324},
{"learn":[0.359848238],"iteration":301,"passed_time":1.091339642,"remaining_time":2.522367781},
{"learn":[0.3596465795],"iteration":302,"passed_time":1.11401048,"remaining_time":2.562591764},
{"learn":[0.3594878168],"iteration":303,"passed_time":1.141190755,"remaining_time":2.612726203},
{"learn":[0.359239336],"iteration":304,"passed_time":1.173179988,"remaining_time":2.673311776},
{"learn":[0.3590682221],"iteration":305,"passed_time":1.175649242,"remaining_time":2.666341746},
{"learn":[0.358906893],"iteration":306,"passed_time":1.178015551,"remaining_time":2.659168655},
{"learn":[0.3587653929],"iteration":307,"passed_time":1.217584212,"remaining_time":2.735611281},
{"learn":[0.3586031532],"iteration":308,"passed_time":1.239456151,"remaining_time":2.771728803},
{"learn":[0.3582269155],"iteration":309,"passed_time":1.246754387,"remaining_time":2.775033957},
{"learn":[0.3580197049],"iteration":310,"passed_time":1.248771674,"remaining_time":2.76657133},
{"learn":[0.3576922701],"iteration":311,"passed_time":1.265323523,"remaining_time":2.790200589},
{"learn":[0.3574848602],"iteration":312,"passed_time":1.275543513,"remaining_time":2.799675378},
{"learn":[0.3572366802],"iteration":313,"passed_time":1.296813176,"remaining_time":2.833165092},
{"learn":[0.3571419477],"iteration":314,"passed_time":1.368842745,"remaining_time":2.976689779},
{"learn":[0.3569913795],"iteration":315,"passed_time":1.372071385,"remaining_time":2.969926669},
{"learn":[0.3567320264],"iteration":316,"passed_time":1.373726976,"remaining_time":2.959796607},
{"learn":[0.3565222279],"iteration":317,"passed_time":1.374997804,"remaining_time":2.948894662},
{"learn":[0.3562835432],"iteration":318,"passed_time":1.431059246,"remaining_time":3.055019896},
{"learn":[0.3560280103],"iteration":319,"passed_time":1.433165446,"remaining_time":3.045476573},
{"learn":[0.3558957063],"iteration":320,"passed_time":1.435235201,"remaining_time":3.035902498},
{"learn":[0.3557774784],"iteration":321,"passed_time":1.45880491,"remaining_time":3.071645122},
{"learn":[0.3555028875],"iteration":322,"passed_time":1.460987279,"remaining_time":3.062193151},
{"learn":[0.3553183038],"iteration":323,"passed_time":1.462924448,"remaining_time":3.052274465},
{"learn":[0.3551749727],"iteration":324,"passed_time":1.46483843,"remaining_time":3.042356739},
{"learn":[0.3550710589],"iteration":325,"passed_time":1.526359621,"remaining_time":3.155725106},
{"learn":[0.3549754692],"iteration":326,"passed_time":1.534491823,"remaining_time":3.158143721},
{"learn":[0.3547756983],"iteration":327,"passed_time":1.547126322,"remaining_time":3.169722221},
{"learn":[0.3546397283],"iteration":328,"passed_time":1.567153916,"remaining_time":3.196231848},
{"learn":[0.3544208697],"iteration":329,"passed_time":1.600202114,"remaining_time":3.248895201},
{"learn":[0.3541494508],"iteration":330,"passed_time":1.611967993,"remaining_time":3.258025943},
{"learn":[0.3538596177],"iteration":331,"passed_time":1.613383401,"remaining_time":3.246205156},
{"learn":[0.3537747749],"iteration":332,"passed_time":1.625723922,"remaining_time":3.256329898},
{"learn":[0.3536325853],"iteration":333,"passed_time":1.627929007,"remaining_time":3.246109936},
{"learn":[0.3534958719],"iteration":334,"passed_time":1.682979038,"remaining_time":3.340838985},
{"learn":[0.3533678797],"iteration":335,"passed_time":1.691387099,"remaining_time":3.342503076},
{"learn":[0.3533064731],"iteration":336,"passed_time":1.705074705,"remaining_time":3.354494152},
{"learn":[0.3529454847],"iteration":337,"passed_time":1.707325512,"remaining_time":3.3439334},
{"learn":[0.3528592637],"iteration":338,"passed_time":1.709470232,"remaining_time":3.333214817},
{"learn":[0.3527187469],"iteration":339,"passed_time":1.762661824,"remaining_time":3.421637658},
{"learn":[0.3525003548],"iteration":340,"passed_time":1.786522296,"remaining_time":3.452546021},
{"learn":[0.352385701],"iteration":341,"passed_time":1.793691349,"remaining_time":3.451020198},
{"learn":[0.3522807383],"iteration":342,"passed_time":1.795693692,"remaining_time":3.439564885},
{"learn":[0.3521301889],"iteration":343,"passed_time":1.797631919,"remaining_time":3.428042264},
{"learn":[0.351991599],"iteration":344,"passed_time":1.852054863,"remaining_time":3.516220101},
{"learn":[0.3517515867],"iteration":345,"passed_time":1.864167792,"remaining_time":3.523600393},
{"learn":[0.3515524575],"iteration":346,"passed_time":1.874722135,"remaining_time":3.527935315},
{"learn":[0.3513647657],"iteration":347,"passed_time":1.89298078,"remaining_time":3.546619162},
{"learn":[0.3512507442],"iteration":348,"passed_time":1.895017937,"remaining_time":3.534832885},
{"learn":[0.3510213272],"iteration":349,"passed_time":1.897036867,"remaining_time":3.523068468},
{"learn":[0.3508662317],"iteration":350,"passed_time":1.934045529,"remaining_time":3.576055693},
{"learn":[0.3507638132],"iteration":351,"passed_time":1.936113852,"remaining_time":3.564209591},
{"learn":[0.3506693112],"iteration":352,"passed_time":1.938142214,"remaining_time":3.552345645},
{"learn":[0.3505260185],"iteration":353,"passed_time":1.978326671,"remaining_time":3.610166749},
{"learn":[0.3503191343],"iteration":354,"passed_time":2.034840958,"remaining_time":3.697105403},
{"learn":[0.3502371403],"iteration":355,"passed_time":2.071310289,"remaining_time":3.746977039},
{"learn":[0.3501127275],"iteration":356,"passed_time":2.093022247,"remaining_time":3.769785168},
{"learn":[0.3500468372],"iteration":357,"passed_time":2.103469779,"remaining_time":3.772144129},
{"learn":[0.3499315183],"iteration":358,"passed_time":2.115585088,"remaining_time":3.777409586},
{"learn":[0.3496148094],"iteration":359,"passed_time":2.117543703,"remaining_time":3.764522138},
{"learn":[0.3494442654],"iteration":360,"passed_time":2.132124624,"remaining_time":3.774037769},
{"learn":[0.3492046003],"iteration":361,"passed_time":2.136338679,"remaining_time":3.765149385},
{"learn":[0.3490549768],"iteration":362,"passed_time":2.145952966,"remaining_time":3.765763194},
{"learn":[0.3488994802],"iteration":363,"passed_time":2.162978322,"remaining_time":3.779269816},
{"learn":[0.348656942],"iteration":364,"passed_time":2.164439363,"remaining_time":3.765531494},
{"learn":[0.3485301804],"iteration":365,"passed_time":2.199372737,"remaining_time":3.809842391},
{"learn":[0.3483767772],"iteration":366,"passed_time":2.201838053,"remaining_time":3.797720674},
{"learn":[0.3482878739],"iteration":367,"passed_time":2.203403916,"remaining_time":3.784106726},
{"learn":[0.3481386814],"iteration":368,"passed_time":2.249854886,"remaining_time":3.847312827},
{"learn":[0.3480379967],"iteration":369,"passed_time":2.251775666,"remaining_time":3.834104513},
{"learn":[0.3477494746],"iteration":370,"passed_time":2.253755655,"remaining_time":3.821057431},
{"learn":[0.3475367565],"iteration":371,"passed_time":2.255725186,"remaining_time":3.808052195},
{"learn":[0.3474404207],"iteration":372,"passed_time":2.257662162,"remaining_time":3.795051409},
{"learn":[0.3473342531],"iteration":373,"passed_time":2.32147657,"remaining_time":3.885680035},
{"learn":[0.3471189447],"iteration":374,"passed_time":2.323690682,"remaining_time":3.872817804},
{"learn":[0.3468945726],"iteration":375,"passed_time":2.325845864,"remaining_time":3.859914412},
{"learn":[0.346832764],"iteration":376,"passed_time":2.362464907,"remaining_time":3.904020258},
{"learn":[0.346651551],"iteration":377,"passed_time":2.36460899,"remaining_time":3.890970349},
{"learn":[0.3464650944],"iteration":378,"passed_time":2.406165914,"remaining_time":3.942556815},
{"learn":[0.3462932479],"iteration":379,"passed_time":2.409115812,"remaining_time":3.93066264},
{"learn":[0.3460950772],"iteration":380,"passed_time":2.43490762,"remaining_time":3.955926029},
{"learn":[0.346045889],"iteration":381,"passed_time":2.436681886,"remaining_time":3.942066507},
{"learn":[0.3459198272],"iteration":382,"passed_time":2.438669302,"remaining_time":3.928613471},
{"learn":[0.3456641005],"iteration":383,"passed_time":2.440803615,"remaining_time":3.9154558},
{"learn":[0.3453451681],"iteration":384,"passed_time":2.480308624,"remaining_time":3.962051439},
{"learn":[0.3452258677],"iteration":385,"passed_time":2.482354388,"remaining_time":3.948615529},
{"learn":[0.3449810248],"iteration":386,"passed_time":2.484233435,"remaining_time":3.934974407},
{"learn":[0.3447133571],"iteration":387,"passed_time":2.485478818,"remaining_time":3.920394425},
{"learn":[0.3445714366],"iteration":388,"passed_time":2.512588706,"remaining_time":3.946508225},
{"learn":[0.3444542186],"iteration":389,"passed_time":2.514327379,"remaining_time":3.932665901},
{"learn":[0.3443298851],"iteration":390,"passed_time":2.516023011,"remaining_time":3.91881845},
{"learn":[0.3442697916],"iteration":391,"passed_time":2.5262795,"remaining_time":3.918311061},
{"learn":[0.344167347],"iteration":392,"passed_time":2.543671691,"remaining_time":3.92877536},
{"learn":[0.3441134222],"iteration":393,"passed_time":2.546257094,"remaining_time":3.916324364},
{"learn":[0.344034247],"iteration":394,"passed_time":2.549008636,"remaining_time":3.904177784},
{"learn":[0.3439888964],"iteration":395,"passed_time":2.571409718,"remaining_time":3.922049166},
{"learn":[0.3436275242],"iteration":396,"passed_time":2.574609798,"remaining_time":3.910553422},
{"learn":[0.3434835466],"iteration":397,"passed_time":2.57686717,"remaining_time":3.897673459},
{"learn":[0.3433285239],"iteration":398,"passed_time":2.622905616,"remaining_time":3.95079267},
{"learn":[0.3431887171],"iteration":399,"passed_time":2.633445836,"remaining_time":3.950168755},
{"learn":[0.3429429027],"iteration":400,"passed_time":2.635096183,"remaining_time":3.936215994},
{"learn":[0.3428591226],"iteration":401,"passed_time":2.667072719,"remaining_time":3.967436532},
{"learn":[0.3427272455],"iteration":402,"passed_time":2.677599484,"remaining_time":3.96656797},
{"learn":[0.3425933659],"iteration":403,"passed_time":2.679725454,"remaining_time":3.953258343},
{"learn":[0.3424918509],"iteration":404,"passed_time":2.747649768,"remaining_time":4.036670647},
{"learn":[0.3424382174],"iteration":405,"passed_time":2.749940145,"remaining_time":4.023311444},
{"learn":[0.342379746],"iteration":406,"passed_time":2.775051786,"remaining_time":4.043257271},
{"learn":[0.3421867836],"iteration":407,"passed_time":2.777296368,"remaining_time":4.029802573},
{"learn":[0.3420448149],"iteration":408,"passed_time":2.80920301,"remaining_time":4.059264008},
{"learn":[0.3419936542],"iteration":409,"passed_time":2.811533911,"remaining_time":4.045865872},
{"learn":[0.3419167258],"iteration":410,"passed_time":2.813655541,"remaining_time":4.032221688},
{"learn":[0.341835277],"iteration":411,"passed_time":2.854443601,"remaining_time":4.073817566},
{"learn":[0.3417327951],"iteration":412,"passed_time":2.856906299,"remaining_time":4.060542367},
{"learn":[0.3415952457],"iteration":413,"passed_time":2.868666867,"remaining_time":4.060480154},
{"learn":[0.3413382256],"iteration":414,"passed_time":2.870796757,"remaining_time":4.04678579},
{"learn":[0.3411571876],"iteration":415,"passed_time":2.89225116,"remaining_time":4.060275667},
{"learn":[0.3410580828],"iteration":416,"passed_time":2.894490469,"remaining_time":4.046733678},
{"learn":[0.3409838674],"iteration":417,"passed_time":2.896531362,"remaining_time":4.032969504},
{"learn":[0.3408628684],"iteration":418,"passed_time":2.898571003,"remaining_time":4.019259553},
{"learn":[0.3407137003],"iteration":419,"passed_time":2.900649189,"remaining_time":4.005658404},
{"learn":[0.3405829009],"iteration":420,"passed_time":2.955223503,"remaining_time":4.064309758},
{"learn":[0.3404139093],"iteration":421,"passed_time":2.957520039,"remaining_time":4.050821286},
{"learn":[0.3401757663],"iteration":422,"passed_time":2.959748611,"remaining_time":4.037293022},
{"learn":[0.3399646634],"iteration":423,"passed_time":2.961900796,"remaining_time":4.023714289},
{"learn":[0.3398547578],"iteration":424,"passed_time":2.964135672,"remaining_time":4.010301203},
{"learn":[0.3396294561],"iteration":425,"passed_time":2.966320935,"remaining_time":3.996873749},
{"learn":[0.339550243],"iteration":426,"passed_time":3.036468629,"remaining_time":4.07469912},
{"learn":[0.3394610057],"iteration":427,"passed_time":3.052614003,"remaining_time":4.079661705},
{"learn":[0.3393524231],"iteration":428,"passed_time":3.082334776,"remaining_time":4.102594772},
{"learn":[0.3391060137],"iteration":429,"passed_time":3.090904273,"remaining_time":4.097245199},
{"learn":[0.3389729482],"iteration":430,"passed_time":3.102516958,"remaining_time":4.095898257},
{"learn":[0.3388471454],"iteration":431,"passed_time":3.103579659,"remaining_time":4.080632514},
{"learn":[0.3387642531],"iteration":432,"passed_time":3.114841397,"remaining_time":4.078787696},
{"learn":[0.3385894624],"iteration":433,"passed_time":3.115911495,"remaining_time":4.063608079},
{"learn":[0.3383774025],"iteration":434,"passed_time":3.122736607,"remaining_time":4.055968237},
{"learn":[0.3381656303],"iteration":435,"passed_time":3.130176865,"remaining_time":4.049127872},
{"learn":[0.3380426416],"iteration":436,"passed_time":3.135226819,"remaining_time":4.039205261},
{"learn":[0.3379422271],"iteration":437,"passed_time":3.142803713,"remaining_time":4.03254723},
{"learn":[0.3378185143],"iteration":438,"passed_time":3.146938233,"remaining_time":4.021485988},
{"learn":[0.337641305],"iteration":439,"passed_time":3.154701542,"remaining_time":4.01507469},
{"learn":[0.3374679643],"iteration":440,"passed_time":3.155802584,"remaining_time":4.000212346},
{"learn":[0.33729751],"iteration":441,"passed_time":3.202682797,"remaining_time":4.043205884},
{"learn":[0.3371448637],"iteration":442,"passed_time":3.204789932,"remaining_time":4.029498854},
{"learn":[0.3370180284],"iteration":443,"passed_time":3.206503459,"remaining_time":4.015351178},
{"learn":[0.336887707],"iteration":444,"passed_time":3.22384838,"remaining_time":4.020754721},
{"learn":[0.3366981172],"iteration":445,"passed_time":3.22597876,"remaining_time":4.007157473},
{"learn":[0.3366763835],"iteration":446,"passed_time":3.227980595,"remaining_time":3.993452503},
{"learn":[0.3364537881],"iteration":447,"passed_time":3.26547258,"remaining_time":4.023528715},
{"learn":[0.3363356752],"iteration":448,"passed_time":3.295588028,"remaining_time":4.044251677},
{"learn":[0.3362134559],"iteration":449,"passed_time":3.29914762,"remaining_time":4.032291536},
{"learn":[0.3361574736],"iteration":450,"passed_time":3.330393362,"remaining_time":4.054070856},
{"learn":[0.3360827533],"iteration":451,"passed_time":3.368927209,"remaining_time":4.084451572},
{"learn":[0.3360145181],"iteration":452,"passed_time":3.376945041,"remaining_time":4.077679774},
{"learn":[0.3359016613],"iteration":453,"passed_time":3.378189684,"remaining_time":4.062756757},
{"learn":[0.3357307554],"iteration":454,"passed_time":3.380452208,"remaining_time":4.049113085},
{"learn":[0.335511925],"iteration":455,"passed_time":3.382263106,"remaining_time":4.034980548},
{"learn":[0.3353630686],"iteration":456,"passed_time":3.401112382,"remaining_time":4.04114666},
{"learn":[0.3352470591],"iteration":457,"passed_time":3.438927011,"remaining_time":4.069647249},
{"learn":[0.335115425],"iteration":458,"passed_time":3.441081535,"remaining_time":4.055828127},
{"learn":[0.3349650123],"iteration":459,"passed_time":3.443114454,"remaining_time":4.041916967},
{"learn":[0.3349068285],"iteration":460,"passed_time":3.507908248,"remaining_time":4.101437193},
{"learn":[0.3347843744],"iteration":461,"passed_time":3.510157488,"remaining_time":4.087585993},
{"learn":[0.3344886238],"iteration":462,"passed_time":3.527975446,"remaining_time":4.091841932},
{"learn":[0.3342791023],"iteration":463,"passed_time":3.541322675,"remaining_time":4.090838262},
{"learn":[0.3342313222],"iteration":464,"passed_time":3.543544426,"remaining_time":4.076981221},
{"learn":[0.3341708853],"iteration":465,"passed_time":3.568206884,"remaining_time":4.088889434},
{"learn":[0.3340127073],"iteration":466,"passed_time":3.575289627,"remaining_time":4.080576812},
{"learn":[0.3338944015],"iteration":467,"passed_time":3.617662756,"remaining_time":4.112385868},
{"learn":[0.3337124269],"iteration":468,"passed_time":3.61903843,"remaining_time":4.09746142},
{"learn":[0.3335917191],"iteration":469,"passed_time":3.620711675,"remaining_time":4.082930187},
{"learn":[0.3334675363],"iteration":470,"passed_time":3.653005,"remaining_time":4.102844256},
{"learn":[0.3333045923],"iteration":471,"passed_time":3.655160234,"remaining_time":4.088823313},
{"learn":[0.3331915274],"iteration":472,"passed_time":3.657237618,"remaining_time":4.074765803},
{"learn":[0.332968729],"iteration":473,"passed_time":3.696385774,"remaining_time":4.10189645},
{"learn":[0.3328927783],"iteration":474,"passed_time":3.711901794,"remaining_time":4.102628299},
{"learn":[0.3327302605],"iteration":475,"passed_time":3.713951804,"remaining_time":4.088467952},
{"learn":[0.3326344225],"iteration":476,"passed_time":3.717811662,"remaining_time":4.076342765},
{"learn":[0.332558907],"iteration":477,"passed_time":3.740982061,"remaining_time":4.085340242},
{"learn":[0.3324026519],"iteration":478,"passed_time":3.743066535,"remaining_time":4.071268611},
{"learn":[0.3322354361],"iteration":479,"passed_time":3.764371036,"remaining_time":4.078068622},
{"learn":[0.33206476],"iteration":480,"passed_time":3.766590109,"remaining_time":4.064158558},
{"learn":[0.3318357215],"iteration":481,"passed_time":3.768165757,"remaining_time":4.049605523},
{"learn":[0.3317326607],"iteration":482,"passed_time":3.828701885,"remaining_time":4.098217132},
{"learn":[0.3316493336],"iteration":483,"passed_time":3.83076892,"remaining_time":4.084042898},
{"learn":[0.3314453856],"iteration":484,"passed_time":3.832799723,"remaining_time":4.069880118},
{"learn":[0.3313504623],"iteration":485,"passed_time":3.868014055,"remaining_time":4.090862602},
{"learn":[0.3312589794],"iteration":486,"passed_time":3.878861196,"remaining_time":4.085946188},
{"learn":[0.3311873666],"iteration":487,"passed_time":3.88053478,"remaining_time":4.071380752},
{"learn":[0.3310935811],"iteration":488,"passed_time":3.940688816,"remaining_time":4.117979519},
{"learn":[0.3310290164],"iteration":489,"passed_time":3.944996318,"remaining_time":4.106016576},
{"learn":[0.3309408189],"iteration":490,"passed_time":3.94709204,"remaining_time":4.091791952},
{"learn":[0.33088361],"iteration":491,"passed_time":3.949099164,"remaining_time":4.077525153},
{"learn":[0.3307875893],"iteration":492,"passed_time":3.951087885,"remaining_time":4.063289164},
{"learn":[0.3306438667],"iteration":493,"passed_time":3.953087431,"remaining_time":4.049113846},
{"learn":[0.3304289511],"iteration":494,"passed_time":4.003369564,"remaining_time":4.084245716},
{"learn":[0.3303657588],"iteration":495,"passed_time":4.005486414,"remaining_time":4.070091034},
{"learn":[0.3302715495],"iteration":496,"passed_time":4.031679737,"remaining_time":4.080351927},
{"learn":[0.3301472698],"iteration":497,"passed_time":4.033230375,"remaining_time":4.0656258},
{"learn":[0.3300608897],"iteration":498,"passed_time":4.034767377,"remaining_time":4.050938789},
{"learn":[0.32997391],"iteration":499,"passed_time":4.073480437,"remaining_time":4.073480437},
{"learn":[0.3298516286],"iteration":500,"passed_time":4.089193299,"remaining_time":4.072869174},
{"learn":[0.3296470507],"iteration":501,"passed_time":4.091702131,"remaining_time":4.059098926},
{"learn":[0.3295132369],"iteration":502,"passed_time":4.103314603,"remaining_time":4.054368505},
{"learn":[0.3294322069],"iteration":503,"passed_time":4.12062316,"remaining_time":4.055216443},
{"learn":[0.3293729617],"iteration":504,"passed_time":4.122437663,"remaining_time":4.040805234},
{"learn":[0.3292432837],"iteration":505,"passed_time":4.124444619,"remaining_time":4.026631703},
{"learn":[0.329092477],"iteration":506,"passed_time":4.126475911,"remaining_time":4.012529831},
{"learn":[0.3288132867],"iteration":507,"passed_time":4.128477479,"remaining_time":3.998446693},
{"learn":[0.3285994433],"iteration":508,"passed_time":4.190674125,"remaining_time":4.042477398},
{"learn":[0.3285141215],"iteration":509,"passed_time":4.192687695,"remaining_time":4.02826857},
{"learn":[0.328349396],"iteration":510,"passed_time":4.217973922,"remaining_time":4.036378176},
{"learn":[0.3280397698],"iteration":511,"passed_time":4.219541121,"remaining_time":4.021750131},
{"learn":[0.3278947195],"iteration":512,"passed_time":4.22149984,"remaining_time":4.007544683},
{"learn":[0.3278387707],"iteration":513,"passed_time":4.223437484,"remaining_time":3.993366959},
{"learn":[0.327740879],"iteration":514,"passed_time":4.273761707,"remaining_time":4.024804714},
{"learn":[0.3274749837],"iteration":515,"passed_time":4.27594763,"remaining_time":4.010772583},
{"learn":[0.3274159504],"iteration":516,"passed_time":4.277888006,"remaining_time":3.99655688},
{"learn":[0.327253082],"iteration":517,"passed_time":4.279542269,"remaining_time":3.982122343},
{"learn":[0.3271880651],"iteration":518,"passed_time":4.323625259,"remaining_time":4.007059248},
{"learn":[0.3270628539],"iteration":519,"passed_time":4.369123543,"remaining_time":4.033037116},
{"learn":[0.326955493],"iteration":520,"passed_time":4.371661457,"remaining_time":4.019243451},
{"learn":[0.3268518308],"iteration":521,"passed_time":4.37379037,"remaining_time":4.005118385},
{"learn":[0.3265324533],"iteration":522,"passed_time":4.376356546,"remaining_time":3.991437997},
{"learn":[0.3264230354],"iteration":523,"passed_time":4.378140426,"remaining_time":3.977089394},
{"learn":[0.3263412551],"iteration":524,"passed_time":4.379706644,"remaining_time":3.962591726},
{"learn":[0.3262585803],"iteration":525,"passed_time":4.381340457,"remaining_time":3.948204138},
{"learn":[0.326208057],"iteration":526,"passed_time":4.382928595,"remaining_time":3.933823957},
{"learn":[0.326053318],"iteration":527,"passed_time":4.384431081,"remaining_time":3.919415663},
{"learn":[0.3259433422],"iteration":528,"passed_time":4.385743192,"remaining_time":3.904886661},
{"learn":[0.3257873712],"iteration":529,"passed_time":4.387041737,"remaining_time":3.890395503},
{"learn":[0.3256661569],"iteration":530,"passed_time":4.388538759,"remaining_time":3.876129337},
{"learn":[0.3256276006],"iteration":531,"passed_time":4.390107391,"remaining_time":3.861974171},
{"learn":[0.3255623609],"iteration":532,"passed_time":4.391675485,"remaining_time":3.847865762},
{"learn":[0.325445531],"iteration":533,"passed_time":4.39345902,"remaining_time":3.833992328},
{"learn":[0.3253895222],"iteration":534,"passed_time":4.39516433,"remaining_time":3.8200961},
{"learn":[0.3253569367],"iteration":535,"passed_time":4.396577801,"remaining_time":3.805992723},
{"learn":[0.3252332051],"iteration":536,"passed_time":4.397940778,"remaining_time":3.791893073},
{"learn":[0.324919582],"iteration":537,"passed_time":4.399240561,"remaining_time":3.777786504},
{"learn":[0.3248718679],"iteration":538,"passed_time":4.400623689,"remaining_time":3.76379874},
{"learn":[0.3247379348],"iteration":539,"passed_time":4.40199107,"remaining_time":3.749844244},
{"learn":[0.324621856],"iteration":540,"passed_time":4.403521249,"remaining_time":3.736074405},
{"learn":[0.3245329524],"iteration":541,"passed_time":4.405137188,"remaining_time":3.7224222},
{"learn":[0.3244102544],"iteration":542,"passed_time":4.406725029,"remaining_time":3.708790678},
{"learn":[0.324314812],"iteration":543,"passed_time":4.408133915,"remaining_time":3.695053429},
{"learn":[0.3242201509],"iteration":544,"passed_time":4.4097166,"remaining_time":3.681506519},
{"learn":[0.3241052647],"iteration":545,"passed_time":4.411320514,"remaining_time":3.668021087},
{"learn":[0.3240226925],"iteration":546,"passed_time":4.412901321,"remaining_time":3.65455996},
{"learn":[0.3239482556],"iteration":547,"passed_time":4.414416448,"remaining_time":3.641088019},
{"learn":[0.3238935169],"iteration":548,"passed_time":4.415765253,"remaining_time":3.627523004},
{"learn":[0.3238560987],"iteration":549,"passed_time":4.417007293,"remaining_time":3.613915058},
{"learn":[0.3237506111],"iteration":550,"passed_time":4.418329387,"remaining_time":3.600417232},
{"learn":[0.3236452431],"iteration":551,"passed_time":4.420431807,"remaining_time":3.587596829},
{"learn":[0.3235055359],"iteration":552,"passed_time":4.422428547,"remaining_time":3.574729766},
{"learn":[0.3234463488],"iteration":553,"passed_time":4.423982449,"remaining_time":3.561545437},
{"learn":[0.3232942599],"iteration":554,"passed_time":4.42522817,"remaining_time":3.54815592},
{"learn":[0.3231807114],"iteration":555,"passed_time":4.435227411,"remaining_time":3.541800306},
{"learn":[0.3230332017],"iteration":556,"passed_time":4.436605519,"remaining_time":3.528574946},
{"learn":[0.3228729311],"iteration":557,"passed_time":4.437932442,"remaining_time":3.515351504},
{"learn":[0.32280356],"iteration":558,"passed_time":4.439504864,"remaining_time":3.502364303},
{"learn":[0.3227304479],"iteration":559,"passed_time":4.441134187,"remaining_time":3.489462576},
{"learn":[0.3226077275],"iteration":560,"passed_time":4.442645121,"remaining_time":3.476508393},
{"learn":[0.3224349085],"iteration":561,"passed_time":4.44422245,"remaining_time":3.463646678},
{"learn":[0.3223392332],"iteration":562,"passed_time":4.445837634,"remaining_time":3.450854433},
{"learn":[0.3222396716],"iteration":563,"passed_time":4.447439458,"remaining_time":3.438091496},
{"learn":[0.322155804],"iteration":564,"passed_time":4.449056949,"remaining_time":3.425380129},
{"learn":[0.3220790537],"iteration":565,"passed_time":4.450454341,"remaining_time":3.412539195},
{"learn":[0.3220354079],"iteration":566,"passed_time":4.451532562,"remaining_time":3.399494884},
{"learn":[0.3218446294],"iteration":567,"passed_time":4.452886646,"remaining_time":3.386702519},
{"learn":[0.321737349],"iteration":568,"passed_time":4.454296284,"remaining_time":3.37399244},
{"learn":[0.3216602701],"iteration":569,"passed_time":4.455570099,"remaining_time":3.361219548},
{"learn":[0.3214907511],"iteration":570,"passed_time":4.456775472,"remaining_time":3.348435512},
{"learn":[0.3212213044],"iteration":571,"passed_time":4.458141896,"remaining_time":3.335812467},
{"learn":[0.3211338619],"iteration":572,"passed_time":4.459696847,"remaining_time":3.323369204},
{"learn":[0.3210559786],"iteration":573,"passed_time":4.461254614,"remaining_time":3.310965968},
{"learn":[0.3209974935],"iteration":574,"passed_time":4.462655658,"remaining_time":3.298484617},
{"learn":[0.3209138177],"iteration":575,"passed_time":4.46398771,"remaining_time":3.285990953},
{"learn":[0.3208587637],"iteration":576,"passed_time":4.465503309,"remaining_time":3.273670537},
{"learn":[0.3207275178],"iteration":577,"passed_time":4.467070933,"remaining_time":3.261425491},
{"learn":[0.3206824984],"iteration":578,"passed_time":4.468731102,"remaining_time":3.249284618},
{"learn":[0.3205834498],"iteration":579,"passed_time":4.470127254,"remaining_time":3.236988701},
{"learn":[0.3204561729],"iteration":580,"passed_time":4.47165253,"remaining_time":3.224823425},
{"learn":[0.3203554303],"iteration":581,"passed_time":4.47325262,"remaining_time":3.212748446},
{"learn":[0.3202978485],"iteration":582,"passed_time":4.474416931,"remaining_time":3.200397702},
{"learn":[0.3200806829],"iteration":583,"passed_time":4.47572021,"remaining_time":3.188184259},
{"learn":[0.3200027318],"iteration":584,"passed_time":4.476946722,"remaining_time":3.175953657},
{"learn":[0.3199010115],"iteration":585,"passed_time":4.478166766,"remaining_time":3.163756043},
{"learn":[0.3198482113],"iteration":586,"passed_time":4.479418164,"remaining_time":3.151617891},
{"learn":[0.3197638528],"iteration":587,"passed_time":4.480669787,"remaining_time":3.139516926},
{"learn":[0.3197052476],"iteration":588,"passed_time":4.482084932,"remaining_time":3.127566905},
{"learn":[0.3196679594],"iteration":589,"passed_time":4.483603203,"remaining_time":3.11572426},
{"learn":[0.319508749],"iteration":590,"passed_time":4.485127079,"remaining_time":3.103920432},
{"learn":[0.3193286254],"iteration":591,"passed_time":4.486310204,"remaining_time":3.091916492},
{"learn":[0.3192917483],"iteration":592,"passed_time":4.487819114,"remaining_time":3.080172646},
{"learn":[0.3190487711],"iteration":593,"passed_time":4.489374786,"remaining_time":3.068495224},
{"learn":[0.318947059],"iteration":594,"passed_time":4.490919239,"remaining_time":3.056844188},
{"learn":[0.3188066323],"iteration":595,"passed_time":4.49247713,"remaining_time":3.045236175},
{"learn":[0.3186746726],"iteration":596,"passed_time":4.493789035,"remaining_time":3.033495781},
{"learn":[0.3185669349],"iteration":597,"passed_time":4.495047484,"remaining_time":3.021754329},
{"learn":[0.3184632327],"iteration":598,"passed_time":4.496313577,"remaining_time":3.010052996},
{"learn":[0.3183825505],"iteration":599,"passed_time":4.497620029,"remaining_time":2.998413353},
{"learn":[0.3183375311],"iteration":600,"passed_time":4.499155423,"remaining_time":2.98696009},
{"learn":[0.318066536],"iteration":601,"passed_time":4.500403285,"remaining_time":2.97534968},
{"learn":[0.3180276677],"iteration":602,"passed_time":4.50162429,"remaining_time":2.963755959},
{"learn":[0.3179752477],"iteration":603,"passed_time":4.502886055,"remaining_time":2.952223307},
{"learn":[0.3178131887],"iteration":604,"passed_time":4.504125919,"remaining_time":2.940710311},
{"learn":[0.3177397451],"iteration":605,"passed_time":4.506207163,"remaining_time":2.929778254},
{"learn":[0.3175242289],"iteration":606,"passed_time":4.508231345,"remaining_time":2.918838416},
{"learn":[0.3174578411],"iteration":607,"passed_time":4.509449745,"remaining_time":2.907408388},
{"learn":[0.3173461763],"iteration":608,"passed_time":4.510954612,"remaining_time":2.896195818},
{"learn":[0.3170970639],"iteration":609,"passed_time":4.512158767,"remaining_time":2.884822819},
{"learn":[0.3169590079],"iteration":610,"passed_time":4.513333259,"remaining_time":2.873464219},
{"learn":[0.316758266],"iteration":611,"passed_time":4.51465204,"remaining_time":2.862230378},
{"learn":[0.3167224707],"iteration":612,"passed_time":4.515907513,"remaining_time":2.850988919},
{"learn":[0.316611828],"iteration":613,"passed_time":4.517091346,"remaining_time":2.839734951},
{"learn":[0.3165773579],"iteration":614,"passed_time":4.518309094,"remaining_time":2.828534961},
{"learn":[0.3164886008],"iteration":615,"passed_time":4.519934169,"remaining_time":2.8176213},
{"learn":[0.3162806109],"iteration":616,"passed_time":4.521518753,"remaining_time":2.806712613},
{"learn":[0.3161864956],"iteration":617,"passed_time":4.523046225,"remaining_time":2.795798799},
{"learn":[0.3160895245],"iteration":618,"passed_time":4.524499218,"remaining_time":2.78486947},
{"learn":[0.3159301811],"iteration":619,"passed_time":4.525698625,"remaining_time":2.773815286},
{"learn":[0.3158291052],"iteration":620,"passed_time":4.526936533,"remaining_time":2.762816338},
{"learn":[0.3157473278],"iteration":621,"passed_time":4.528223082,"remaining_time":2.751878336},
{"learn":[0.3155344504],"iteration":622,"passed_time":4.529508319,"remaining_time":2.740970524},
{"learn":[0.3154176065],"iteration":623,"passed_time":4.530774214,"remaining_time":2.730081898},
{"learn":[0.3151992279],"iteration":624,"passed_time":4.532046405,"remaining_time":2.719227843},
{"learn":[0.31512561],"iteration":625,"passed_time":4.533275811,"remaining_time":2.708378839},
{"learn":[0.315026411],"iteration":626,"passed_time":4.534580126,"remaining_time":2.697605083},
{"learn":[0.3149670814],"iteration":627,"passed_time":4.535782867,"remaining_time":2.686801316},
{"learn":[0.3148183637],"iteration":628,"passed_time":4.537215165,"remaining_time":2.676163476},
{"learn":[0.3147108765],"iteration":629,"passed_time":4.538682815,"remaining_time":2.665575621},
{"learn":[0.3146460847],"iteration":630,"passed_time":4.540055115,"remaining_time":2.654960915},
{"learn":[0.3145192535],"iteration":631,"passed_time":4.541251277,"remaining_time":2.644272895},
{"learn":[0.314423617],"iteration":632,"passed_time":4.542427814,"remaining_time":2.633603488},
{"learn":[0.3143926957],"iteration":633,"passed_time":4.543660593,"remaining_time":2.622996494},
{"learn":[0.3143507087],"iteration":634,"passed_time":4.545212322,"remaining_time":2.612602358},
{"learn":[0.3142703151],"iteration":635,"passed_time":4.54680196,"remaining_time":2.602257726},
{"learn":[0.3142128709],"iteration":636,"passed_time":4.548083538,"remaining_time":2.59176503},
{"learn":[0.3140807472],"iteration":637,"passed_time":4.549326388,"remaining_time":2.581279236},
{"learn":[0.3140365024],"iteration":638,"passed_time":4.550571946,"remaining_time":2.5708239},
{"learn":[0.3138703553],"iteration":639,"passed_time":4.551839126,"remaining_time":2.560409508},
{"learn":[0.3137479841],"iteration":640,"passed_time":4.553092835,"remaining_time":2.550016112},
{"learn":[0.3136518091],"iteration":641,"passed_time":4.55433832,"remaining_time":2.539646602},
{"learn":[0.3134192475],"iteration":642,"passed_time":4.555613167,"remaining_time":2.529321774},
{"learn":[0.3133399474],"iteration":643,"passed_time":4.556759249,"remaining_time":2.518953871},
{"learn":[0.3131898134],"iteration":644,"passed_time":4.55800054,"remaining_time":2.508666964},
{"learn":[0.3131106734],"iteration":645,"passed_time":4.559209423,"remaining_time":2.498390303},
{"learn":[0.3129947959],"iteration":646,"passed_time":4.56070355,"remaining_time":2.4882973},
{"learn":[0.3128304908],"iteration":647,"passed_time":4.562086001,"remaining_time":2.478170174},
{"learn":[0.312699984],"iteration":648,"passed_time":4.563438142,"remaining_time":2.468053602},
{"learn":[0.3126390846],"iteration":649,"passed_time":4.564624237,"remaining_time":2.457874589},
{"learn":[0.3124964712],"iteration":650,"passed_time":4.565876749,"remaining_time":2.44775881},
{"learn":[0.3124248306],"iteration":651,"passed_time":4.567068942,"remaining_time":2.437638024},
{"learn":[0.312307135],"iteration":652,"passed_time":4.568303971,"remaining_time":2.427567347},
{"learn":[0.3122154381],"iteration":653,"passed_time":4.569517028,"remaining_time":2.417512067},
{"learn":[0.3120995653],"iteration":654,"passed_time":4.570831671,"remaining_time":2.407537293},
{"learn":[0.312024496],"iteration":655,"passed_time":4.572055907,"remaining_time":2.397541512},
{"learn":[0.3118765783],"iteration":656,"passed_time":4.573367858,"remaining_time":2.387618227},
{"learn":[0.3118041994],"iteration":657,"passed_time":4.574987493,"remaining_time":2.377881037},
{"learn":[0.3115375305],"iteration":658,"passed_time":4.576596166,"remaining_time":2.368162811},
{"learn":[0.3114207729],"iteration":659,"passed_time":4.57817742,"remaining_time":2.358455035},
{"learn":[0.3111793824],"iteration":660,"passed_time":4.579487774,"remaining_time":2.348632913},
{"learn":[0.3110983878],"iteration":661,"passed_time":4.581028739,"remaining_time":2.33895425},
{"learn":[0.3109684408],"iteration":662,"passed_time":4.582461067,"remaining_time":2.329244917},
{"learn":[0.3108591966],"iteration":663,"passed_time":4.583800756,"remaining_time":2.319513636},
{"learn":[0.3107756816],"iteration":664,"passed_time":4.585178072,"remaining_time":2.309826548},
{"learn":[0.3106583765],"iteration":665,"passed_time":4.586590676,"remaining_time":2.300182111},
{"learn":[0.3103662516],"iteration":666,"passed_time":4.587997757,"remaining_time":2.2905596},
{"learn":[0.3102343203],"iteration":667,"passed_time":4.589163249,"remaining_time":2.280841615},
{"learn":[0.3100871666],"iteration":668,"passed_time":4.590430202,"remaining_time":2.271199397},
{"learn":[0.3099683973],"iteration":669,"passed_time":4.591721833,"remaining_time":2.261594336},
{"learn":[0.3099212863],"iteration":670,"passed_time":4.592954879,"remaining_time":2.251985328},
{"learn":[0.3096959386],"iteration":671,"passed_time":4.594175422,"remaining_time":2.242395146},
{"learn":[0.3095987706],"iteration":672,"passed_time":4.595428854,"remaining_time":2.232845818},
{"learn":[0.3094931775],"iteration":673,"passed_time":4.596634343,"remaining_time":2.223297917},
{"learn":[0.3093693784],"iteration":674,"passed_time":4.59788055,"remaining_time":2.213794339},
{"learn":[0.3092758149],"iteration":675,"passed_time":4.599145913,"remaining_time":2.204324373},
{"learn":[0.3090556145],"iteration":676,"passed_time":4.600401185,"remaining_time":2.19487383},
{"learn":[0.3089308054],"iteration":677,"passed_time":4.601650809,"remaining_time":2.18544478},
{"learn":[0.3087375342],"iteration":678,"passed_time":4.602898796,"remaining_time":2.176039048},
{"learn":[0.3086599236],"iteration":679,"passed_time":4.604126795,"remaining_time":2.166647904},
{"learn":[0.3084961515],"iteration":680,"passed_time":4.605460455,"remaining_time":2.157330228},
{"learn":[0.3082633243],"iteration":681,"passed_time":4.606665969,"remaining_time":2.147976214},
{"learn":[0.3082050154],"iteration":682,"passed_time":4.607891923,"remaining_time":2.138655548},
{"learn":[0.3080574234],"iteration":683,"passed_time":4.609166866,"remaining_time":2.129381184},
{"learn":[0.3079016582],"iteration":684,"passed_time":4.610580024,"remaining_time":2.120193734},
{"learn":[0.3077012068],"iteration":685,"passed_time":4.611988465,"remaining_time":2.11102679},
{"learn":[0.3076379463],"iteration":686,"passed_time":4.61324433,"remaining_time":2.101812919},
{"learn":[0.3076014509],"iteration":687,"passed_time":4.614483392,"remaining_time":2.092614562},
{"learn":[0.3075326316],"iteration":688,"passed_time":4.615771216,"remaining_time":2.083461318},
{"learn":[0.3074099675],"iteration":689,"passed_time":4.61701432,"remaining_time":2.074310782},
{"learn":[0.3073593917],"iteration":690,"passed_time":4.618184902,"remaining_time":2.065150701},
{"learn":[0.3072433881],"iteration":691,"passed_time":4.619429738,"remaining_time":2.056046762},
{"learn":[0.3069742808],"iteration":692,"passed_time":4.620683181,"remaining_time":2.046969317},
{"learn":[0.3068700709],"iteration":693,"passed_time":4.62196582,"remaining_time":2.037927292},
{"learn":[0.3067904529],"iteration":694,"passed_time":4.623156647,"remaining_time":2.028867306},
{"learn":[0.3067280279],"iteration":695,"passed_time":4.624384369,"remaining_time":2.019846046},
{"learn":[0.3065264153],"iteration":696,"passed_time":4.625902677,"remaining_time":2.010973473},
{"learn":[0.3064917346],"iteration":697,"passed_time":4.627332857,"remaining_time":2.002083844},
{"learn":[0.3064336685],"iteration":698,"passed_time":4.628740262,"remaining_time":1.99320575},
{"learn":[0.3063385737],"iteration":699,"passed_time":4.629875877,"remaining_time":1.984232519},
{"learn":[0.3062124645],"iteration":700,"passed_time":4.631070619,"remaining_time":1.975306869},
{"learn":[0.306126474],"iteration":701,"passed_time":4.632334931,"remaining_time":1.966432777},
{"learn":[0.306012077],"iteration":702,"passed_time":4.633625129,"remaining_time":1.957591271},
{"learn":[0.3058910599],"iteration":703,"passed_time":4.634913998,"remaining_time":1.948770658},
{"learn":[0.305802001],"iteration":704,"passed_time":4.636110092,"remaining_time":1.939932592},
{"learn":[0.3055965679],"iteration":705,"passed_time":4.637322885,"remaining_time":1.931123128},
{"learn":[0.305522561],"iteration":706,"passed_time":4.638544521,"remaining_time":1.922338819},
{"learn":[0.3054082268],"iteration":707,"passed_time":4.640081663,"remaining_time":1.913705997},
{"learn":[0.3052956065],"iteration":708,"passed_time":4.641311214,"remaining_time":1.904966944},
{"learn":[0.3052388879],"iteration":709,"passed_time":4.642593139,"remaining_time":1.896270437},
{"learn":[0.3051640402],"iteration":710,"passed_time":4.643807785,"remaining_time":1.88756744},
{"learn":[0.3050547314],"iteration":711,"passed_time":4.645025899,"remaining_time":1.878886881},
{"learn":[0.3050185908],"iteration":712,"passed_time":4.646259296,"remaining_time":1.870233405},
{"learn":[0.304964734],"iteration":713,"passed_time":4.647539377,"remaining_time":1.861619414},
{"learn":[0.304898614],"iteration":714,"passed_time":4.648785561,"remaining_time":1.853012427},
{"learn":[0.3046871825],"iteration":715,"passed_time":4.649994906,"remaining_time":1.844411387},
{"learn":[0.3045262545],"iteration":716,"passed_time":4.651284031,"remaining_time":1.835862456},
{"learn":[0.3044294337],"iteration":717,"passed_time":4.653399801,"remaining_time":1.827658418},
{"learn":[0.3043649365],"iteration":718,"passed_time":4.655414719,"remaining_time":1.8194319},
{"learn":[0.3043343481],"iteration":719,"passed_time":4.656743282,"remaining_time":1.810955721},
{"learn":[0.3041844035],"iteration":720,"passed_time":4.657957619,"remaining_time":1.802455167},
{"learn":[0.3040522654],"iteration":721,"passed_time":4.659305438,"remaining_time":1.794026194},
{"learn":[0.3039412168],"iteration":722,"passed_time":4.660477431,"remaining_time":1.785549444},
{"learn":[0.3038960586],"iteration":723,"passed_time":4.661423652,"remaining_time":1.777006806},
{"learn":[0.3038014399],"iteration":724,"passed_time":4.662730205,"remaining_time":1.768621802},
{"learn":[0.3037799338],"iteration":725,"passed_time":4.663321665,"remaining_time":1.759986414},
{"learn":[0.3037538606],"iteration":726,"passed_time":4.664438289,"remaining_time":1.751570361},
{"learn":[0.3036057722],"iteration":727,"passed_time":4.66564857,"remaining_time":1.743209356},
{"learn":[0.3034482091],"iteration":728,"passed_time":4.666846491,"remaining_time":1.734863373},
{"learn":[0.3033992617],"iteration":729,"passed_time":4.668075082,"remaining_time":1.726548318},
{"learn":[0.3033089691],"iteration":730,"passed_time":4.66928441,"remaining_time":1.718245563},
{"learn":[0.3031959174],"iteration":731,"passed_time":4.67058592,"remaining_time":1.709995938},
{"learn":[0.3030480451],"iteration":732,"passed_time":4.671760433,"remaining_time":1.701719012},
{"learn":[0.3029210924],"iteration":733,"passed_time":4.673008026,"remaining_time":1.693487922},
{"learn":[0.3028164226],"iteration":734,"passed_time":4.674291304,"remaining_time":1.685288701},
{"learn":[0.3027465305],"iteration":735,"passed_time":4.675590678,"remaining_time":1.677114047},
{"learn":[0.3026773869],"iteration":736,"passed_time":4.678026895,"remaining_time":1.669363736},
{"learn":[0.3025599698],"iteration":737,"passed_time":4.679526482,"remaining_time":1.66129531},
{"learn":[0.3024247852],"iteration":738,"passed_time":4.68066599,"remaining_time":1.653117488},
{"learn":[0.3023876667],"iteration":739,"passed_time":4.681933566,"remaining_time":1.645003686},
{"learn":[0.3023436282],"iteration":740,"passed_time":4.683203872,"remaining_time":1.636909316},
{"learn":[0.3022542798],"iteration":741,"passed_time":4.684455763,"remaining_time":1.628826936},
{"learn":[0.3021627748],"iteration":742,"passed_time":4.685697699,"remaining_time":1.6207595},
{"learn":[0.3020052466],"iteration":743,"passed_time":4.686963471,"remaining_time":1.612718614},
{"learn":[0.3018578073],"iteration":744,"passed_time":4.688216339,"remaining_time":1.604691499},
{"learn":[0.3017390734],"iteration":745,"passed_time":4.689458124,"remaining_time":1.596678771},
{"learn":[0.3016928534],"iteration":746,"passed_time":4.690701564,"remaining_time":1.588684733},
{"learn":[0.3014879579],"iteration":747,"passed_time":4.691946502,"remaining_time":1.580709249},
{"learn":[0.3014449314],"iteration":748,"passed_time":4.693243199,"remaining_time":1.572769083},
{"learn":[0.3013213594],"iteration":749,"passed_time":4.694477724,"remaining_time":1.564825908},
{"learn":[0.3012524095],"iteration":750,"passed_time":4.695795943,"remaining_time":1.556928348},
{"learn":[0.3011782468],"iteration":751,"passed_time":4.697003286,"remaining_time":1.549011722},
{"learn":[0.3010060862],"iteration":752,"passed_time":4.699533538,"remaining_time":1.541546858},
{"learn":[0.3008342852],"iteration":753,"passed_time":4.701954196,"remaining_time":1.534059327},
{"learn":[0.3006241201],"iteration":754,"passed_time":4.703360838,"remaining_time":1.526256166},
{"learn":[0.3004823102],"iteration":755,"passed_time":4.704656736,"remaining_time":1.518434185},
{"learn":[0.3004270545],"iteration":756,"passed_time":4.705893553,"remaining_time":1.51061048},
{"learn":[0.30031053],"iteration":757,"passed_time":4.707150519,"remaining_time":1.502810588},
{"learn":[0.3002297184],"iteration":758,"passed_time":4.708386066,"remaining_time":1.495021135},
{"learn":[0.3001493607],"iteration":759,"passed_time":4.709695541,"remaining_time":1.487272276},
{"learn":[0.3000749546],"iteration":760,"passed_time":4.711000626,"remaining_time":1.479538961},
{"learn":[0.2999569562],"iteration":761,"passed_time":4.712166474,"remaining_time":1.47177903},
{"learn":[0.2998801295],"iteration":762,"passed_time":4.71337913,"remaining_time":1.464050923},
{"learn":[0.2997576207],"iteration":763,"passed_time":4.714623094,"remaining_time":1.456349542},
{"learn":[0.299650948],"iteration":764,"passed_time":4.71583057,"remaining_time":1.448653835},
{"learn":[0.299482314],"iteration":765,"passed_time":4.717121532,"remaining_time":1.441000572},
{"learn":[0.2993088892],"iteration":766,"passed_time":4.718390885,"remaining_time":1.433357335},
{"learn":[0.2990428283],"iteration":767,"passed_time":4.71964456,"remaining_time":1.425725961},
{"learn":[0.2990216568],"iteration":768,"passed_time":4.720795679,"remaining_time":1.418080366},
{"learn":[0.2989903019],"iteration":769,"passed_time":4.721995314,"remaining_time":1.410466133},
{"learn":[0.2989045028],"iteration":770,"passed_time":4.723243502,"remaining_time":1.40288296},
{"learn":[0.29880187],"iteration":771,"passed_time":4.724515079,"remaining_time":1.395323106},
{"learn":[0.2986623884],"iteration":772,"passed_time":4.725728485,"remaining_time":1.38776244},
{"learn":[0.2986351446],"iteration":773,"passed_time":4.726970565,"remaining_time":1.380226547},
{"learn":[0.2986101629],"iteration":774,"passed_time":4.728204423,"remaining_time":1.37270451},
{"learn":[0.2985599301],"iteration":775,"passed_time":4.729439784,"remaining_time":1.365199113},
{"learn":[0.2985180227],"iteration":776,"passed_time":4.730636543,"remaining_time":1.357698776},
{"learn":[0.2984041259],"iteration":777,"passed_time":4.731885229,"remaining_time":1.350229461},
{"learn":[0.2983577799],"iteration":778,"passed_time":4.733072768,"remaining_time":1.34275877},
{"learn":[0.2983315828],"iteration":779,"passed_time":4.734331817,"remaining_time":1.335324359},
{"learn":[0.2982691882],"iteration":780,"passed_time":4.735528003,"remaining_time":1.327888134},
{"learn":[0.298162376],"iteration":781,"passed_time":4.736758727,"remaining_time":1.320477497},
{"learn":[0.2981280319],"iteration":782,"passed_time":4.738811876,"remaining_time":1.313310571},
{"learn":[0.2980621902],"iteration":783,"passed_time":4.740033581,"remaining_time":1.305927619},
{"learn":[0.2979466869],"iteration":784,"passed_time":4.741282219,"remaining_time":1.298567742},
{"learn":[0.297895087],"iteration":785,"passed_time":4.742588242,"remaining_time":1.291239038},
{"learn":[0.2977946145],"iteration":786,"passed_time":4.743899475,"remaining_time":1.28392705},
{"learn":[0.2976686839],"iteration":787,"passed_time":4.745157026,"remaining_time":1.27661585},
{"learn":[0.2975752236],"iteration":788,"passed_time":4.746406461,"remaining_time":1.269317824},
{"learn":[0.2974927194],"iteration":789,"passed_time":4.74759741,"remaining_time":1.262019565},
{"learn":[0.2974244413],"iteration":790,"passed_time":4.749109352,"remaining_time":1.254821561},
{"learn":[0.2973858348],"iteration":791,"passed_time":4.751256347,"remaining_time":1.247804697},
{"learn":[0.2972320107],"iteration":792,"passed_time":4.753309295,"remaining_time":1.240775566},
{"learn":[0.2971535392],"iteration":793,"passed_time":4.754541124,"remaining_time":1.233545934},
{"learn":[0.2970488165],"iteration":794,"passed_time":4.755814959,"remaining_time":1.226342222},
{"learn":[0.2970115442],"iteration":795,"passed_time":4.757045512,"remaining_time":1.219142317},
{"learn":[0.2969740847],"iteration":796,"passed_time":4.758286362,"remaining_time":1.211960014},
{"learn":[0.2968453016],"iteration":797,"passed_time":4.759545465,"remaining_time":1.204797223},
{"learn":[0.2968180206],"iteration":798,"passed_time":4.760737155,"remaining_time":1.19763225},
{"learn":[0.2966135913],"iteration":799,"passed_time":4.762007174,"remaining_time":1.190501794},
{"learn":[0.296489408],"iteration":800,"passed_time":4.763200686,"remaining_time":1.183366962},
{"learn":[0.2963267513],"iteration":801,"passed_time":4.76449895,"remaining_time":1.176272808},
{"learn":[0.2962605341],"iteration":802,"passed_time":4.765698377,"remaining_time":1.169168842},
{"learn":[0.2961301341],"iteration":803,"passed_time":4.766913046,"remaining_time":1.16208328},
{"learn":[0.2960531196],"iteration":804,"passed_time":4.768124966,"remaining_time":1.155011638},
{"learn":[0.2956024624],"iteration":805,"passed_time":4.769406281,"remaining_time":1.147971239},
{"learn":[0.2955058846],"iteration":806,"passed_time":4.77068463,"remaining_time":1.140944404},
{"learn":[0.2953318407],"iteration":807,"passed_time":4.773086711,"remaining_time":1.134198822},
{"learn":[0.2952732946],"iteration":808,"passed_time":4.775705924,"remaining_time":1.127515243},
{"learn":[0.2951387438],"iteration":809,"passed_time":4.777120299,"remaining_time":1.120559083},
{"learn":[0.2951046873],"iteration":810,"passed_time":4.778420924,"remaining_time":1.11359008},
{"learn":[0.2950623949],"iteration":811,"passed_time":4.779636832,"remaining_time":1.106615424},
{"learn":[0.2950373949],"iteration":812,"passed_time":4.780963824,"remaining_time":1.099680486},
{"learn":[0.2947762967],"iteration":813,"passed_time":4.782219726,"remaining_time":1.092743082},
{"learn":[0.2947478463],"iteration":814,"passed_time":4.783502466,"remaining_time":1.085825713},
{"learn":[0.2945749632],"iteration":815,"passed_time":4.784759505,"remaining_time":1.078916359},
{"learn":[0.2945323769],"iteration":816,"passed_time":4.786033969,"remaining_time":1.072024745},
{"learn":[0.2944994838],"iteration":817,"passed_time":4.787319728,"remaining_time":1.065149377},
{"learn":[0.2943906063],"iteration":818,"passed_time":4.788673886,"remaining_time":1.058302776},
{"learn":[0.2943351433],"iteration":819,"passed_time":4.789989136,"remaining_time":1.05146103},
{"learn":[0.2942983338],"iteration":820,"passed_time":4.791323037,"remaining_time":1.044636813},
{"learn":[0.2942191742],"iteration":821,"passed_time":4.792614358,"remaining_time":1.037816734},
{"learn":[0.2941370652],"iteration":822,"passed_time":4.793957712,"remaining_time":1.031021282},
{"learn":[0.2940920122],"iteration":823,"passed_time":4.795163162,"remaining_time":1.024209607},
{"learn":[0.2940216542],"iteration":824,"passed_time":4.796504904,"remaining_time":1.017440434},
{"learn":[0.2938143139],"iteration":825,"passed_time":4.797798787,"remaining_time":1.010674321},
{"learn":[0.2936978849],"iteration":826,"passed_time":4.799063493,"remaining_time":1.003915338},
{"learn":[0.2934681841],"iteration":827,"passed_time":4.800377243,"remaining_time":0.9971798137},
{"learn":[0.2934290832],"iteration":828,"passed_time":4.801686613,"remaining_time":0.9904564667},
{"learn":[0.293340596],"iteration":829,"passed_time":4.802930568,"remaining_time":0.983732767},
{"learn":[0.2932545078],"iteration":830,"passed_time":4.804189829,"remaining_time":0.9770253683},
{"learn":[0.2932076534],"iteration":831,"passed_time":4.80540972,"remaining_time":0.9703231165},
{"learn":[0.2931473612],"iteration":832,"passed_time":4.806739208,"remaining_time":0.9636559997},
{"learn":[0.2931051008],"iteration":833,"passed_time":4.807986924,"remaining_time":0.956985407},
{"learn":[0.2928917165],"iteration":834,"passed_time":4.809206465,"remaining_time":0.9503222357},
{"learn":[0.2926918971],"iteration":835,"passed_time":4.810504579,"remaining_time":0.9436875012},
{"learn":[0.2926474917],"iteration":836,"passed_time":4.811750235,"remaining_time":0.9370553026},
{"learn":[0.2924415887],"iteration":837,"passed_time":4.813033932,"remaining_time":0.9304433138},
{"learn":[0.2923835838],"iteration":838,"passed_time":4.814279713,"remaining_time":0.9238367507},
{"learn":[0.2923327353],"iteration":839,"passed_time":4.815549452,"remaining_time":0.9172475146},
{"learn":[0.2922931344],"iteration":840,"passed_time":4.816868341,"remaining_time":0.9106802214},
{"learn":[0.2920993336],"iteration":841,"passed_time":4.818146037,"remaining_time":0.9041176648},
{"learn":[0.2920201613],"iteration":842,"passed_time":4.81948369,"remaining_time":0.897578813},
{"learn":[0.2917057829],"iteration":843,"passed_time":4.820723674,"remaining_time":0.8910342336},
{"learn":[0.2913561402],"iteration":844,"passed_time":4.822290922,"remaining_time":0.8845622402},
{"learn":[0.2913141728],"iteration":845,"passed_time":4.823811177,"remaining_time":0.8780932875},
{"learn":[0.2912197265],"iteration":846,"passed_time":4.825153934,"remaining_time":0.8716039573},
{"learn":[0.2911289232],"iteration":847,"passed_time":4.826652802,"remaining_time":0.8651547476},
{"learn":[0.2908520812],"iteration":848,"passed_time":4.827929192,"remaining_time":0.8586776302},
{"learn":[0.290783514],"iteration":849,"passed_time":4.82918501,"remaining_time":0.8522091194},
{"learn":[0.2907375096],"iteration":850,"passed_time":4.830383327,"remaining_time":0.8457427917},
{"learn":[0.2905299962],"iteration":851,"passed_time":4.832510679,"remaining_time":0.8394502119},
{"learn":[0.2903494644],"iteration":852,"passed_time":4.834269906,"remaining_time":0.8331039581},
{"learn":[0.2902808105],"iteration":853,"passed_time":4.835311085,"remaining_time":0.8266456891},
{"learn":[0.2900894264],"iteration":854,"passed_time":4.83692319,"remaining_time":0.8202969153},
{"learn":[0.2899659138],"iteration":855,"passed_time":4.838160079,"remaining_time":0.813896088},
{"learn":[0.2899037707],"iteration":856,"passed_time":4.839263312,"remaining_time":0.8074850101},
{"learn":[0.2898161464],"iteration":857,"passed_time":4.840331851,"remaining_time":0.8010805628},
{"learn":[0.2897689345],"iteration":858,"passed_time":4.841584488,"remaining_time":0.7947187577},
{"learn":[0.2896530758],"iteration":859,"passed_time":4.842832127,"remaining_time":0.7883680206},
{"learn":[0.2895035452],"iteration":860,"passed_time":4.84400601,"remaining_time":0.7820172305},
{"learn":[0.2894098657],"iteration":861,"passed_time":4.845157407,"remaining_time":0.7756748517},
{"learn":[0.2893820245],"iteration":862,"passed_time":4.846232147,"remaining_time":0.7693323339},
{"learn":[0.2892802171],"iteration":863,"passed_time":4.847472853,"remaining_time":0.7630281343},
{"learn":[0.2891866951],"iteration":864,"passed_time":4.848680522,"remaining_time":0.7567304861},
{"learn":[0.2891233107],"iteration":865,"passed_time":4.849945116,"remaining_time":0.7504534013},
{"learn":[0.2889960764],"iteration":866,"passed_time":4.85116316,"remaining_time":0.7441807384},
{"learn":[0.2887632191],"iteration":867,"passed_time":4.852372717,"remaining_time":0.7379184316},
{"learn":[0.2884587651],"iteration":868,"passed_time":4.853609726,"remaining_time":0.731671892},
{"learn":[0.2883795033],"iteration":869,"passed_time":4.854866395,"remaining_time":0.7254398061},
{"learn":[0.2883092402],"iteration":870,"passed_time":4.856070823,"remaining_time":0.7192114077},
{"learn":[0.28806077],"iteration":871,"passed_time":4.857315123,"remaining_time":0.7130003851},
{"learn":[0.2880129089],"iteration":872,"passed_time":4.858501228,"remaining_time":0.7067922748},
{"learn":[0.2879278669],"iteration":873,"passed_time":4.859797367,"remaining_time":0.7006115198},
{"learn":[0.2879086158],"iteration":874,"passed_time":4.860993104,"remaining_time":0.6944275863},
{"learn":[0.2877863601],"iteration":875,"passed_time":4.862203605,"remaining_time":0.6882571313},
{"learn":[0.2877448871],"iteration":876,"passed_time":4.863577363,"remaining_time":0.6821208845},
{"learn":[0.2876897818],"iteration":877,"passed_time":4.864928044,"remaining_time":0.6759922794},
{"learn":[0.2874411876],"iteration":878,"passed_time":4.866131371,"remaining_time":0.6698542615},
{"learn":[0.2874111295],"iteration":879,"passed_time":4.867305329,"remaining_time":0.6637234539},
{"learn":[0.2873510172],"iteration":880,"passed_time":4.868562449,"remaining_time":0.6576151321},
{"learn":[0.2872047952],"iteration":881,"passed_time":4.869716288,"remaining_time":0.6515039932},
{"learn":[0.2870962924],"iteration":882,"passed_time":4.870981863,"remaining_time":0.6454188878},
{"learn":[0.2870648864],"iteration":883,"passed_time":4.872255905,"remaining_time":0.6393457975},
{"learn":[0.2869453838],"iteration":884,"passed_time":4.873463578,"remaining_time":0.6332749282},
{"learn":[0.2868029729],"iteration":885,"passed_time":4.874736287,"remaining_time":0.6272234048},
{"learn":[0.2867730373],"iteration":886,"passed_time":4.876293594,"remaining_time":0.6212189134},
{"learn":[0.2866483723],"iteration":887,"passed_time":4.877574344,"remaining_time":0.6151895569},
{"learn":[0.2863220428],"iteration":888,"passed_time":4.878859963,"remaining_time":0.6091714914},
{"learn":[0.2862711071],"iteration":889,"passed_time":4.880081652,"remaining_time":0.6031561592},
{"learn":[0.2861744282],"iteration":890,"passed_time":4.881277588,"remaining_time":0.5971484367},
{"learn":[0.2861666525],"iteration":891,"passed_time":4.882812112,"remaining_time":0.5911924978},
{"learn":[0.2860971155],"iteration":892,"passed_time":4.88400173,"remaining_time":0.5852051345},
{"learn":[0.2860151241],"iteration":893,"passed_time":4.885182995,"remaining_time":0.579227514},
{"learn":[0.2858902029],"iteration":894,"passed_time":4.886369408,"remaining_time":0.5732612154},
{"learn":[0.2856681653],"iteration":895,"passed_time":4.88806662,"remaining_time":0.5673648756},
{"learn":[0.2855825065],"iteration":896,"passed_time":4.889150685,"remaining_time":0.5614074923},
{"learn":[0.2855532495],"iteration":897,"passed_time":4.890314869,"remaining_time":0.5554700631},
{"learn":[0.28541263],"iteration":898,"passed_time":4.891757156,"remaining_time":0.549574497},
{"learn":[0.285276148],"iteration":899,"passed_time":4.892984958,"remaining_time":0.5436649953},
{"learn":[0.2851915938],"iteration":900,"passed_time":4.894194278,"remaining_time":0.5377638551},
{"learn":[0.2850672186],"iteration":901,"passed_time":4.895457996,"remaining_time":0.5318790284},
{"learn":[0.2850130564],"iteration":902,"passed_time":4.896792146,"remaining_time":0.5260120024},
{"learn":[0.2847721075],"iteration":903,"passed_time":4.898311366,"remaining_time":0.5201746584},
{"learn":[0.28471437],"iteration":904,"passed_time":4.89954484,"remaining_time":0.5143168617},
{"learn":[0.2846101319],"iteration":905,"passed_time":4.900670327,"remaining_time":0.5084580693},
{"learn":[0.2841998236],"iteration":906,"passed_time":4.901882995,"remaining_time":0.5026186533},
{"learn":[0.2840643582],"iteration":907,"passed_time":4.903100548,"remaining_time":0.4967899233},
{"learn":[0.2839528977],"iteration":908,"passed_time":4.904262361,"remaining_time":0.490965759},
{"learn":[0.2837920625],"iteration":909,"passed_time":4.905418684,"remaining_time":0.4851512984},
{"learn":[0.2837140548],"iteration":910,"passed_time":4.906676369,"remaining_time":0.4793569669},
{"learn":[0.2836480244],"iteration":911,"passed_time":4.907882388,"remaining_time":0.4735675988},
{"learn":[0.2836036214],"iteration":912,"passed_time":4.909485825,"remaining_time":0.467826141},
{"learn":[0.2835017162],"iteration":913,"passed_time":4.910940802,"remaining_time":0.4620797692},
{"learn":[0.2832843594],"iteration":914,"passed_time":4.912290023,"remaining_time":0.456332953},
{"learn":[0.2830081772],"iteration":915,"passed_time":4.913443726,"remaining_time":0.4505778089},
{"learn":[0.2829626995],"iteration":916,"passed_time":4.914605764,"remaining_time":0.4448334552},
{"learn":[0.2827584543],"iteration":917,"passed_time":4.915800417,"remaining_time":0.4391019981},
{"learn":[0.2827282118],"iteration":918,"passed_time":4.917052919,"remaining_time":0.433385513},
{"learn":[0.2826467194],"iteration":919,"passed_time":4.918294387,"remaining_time":0.4276777727},
{"learn":[0.2826267868],"iteration":920,"passed_time":4.91948002,"remaining_time":0.421974942},
{"learn":[0.2825855452],"iteration":921,"passed_time":4.920636311,"remaining_time":0.4162794276},
{"learn":[0.2824984508],"iteration":922,"passed_time":4.921840012,"remaining_time":0.4105977041},
{"learn":[0.2824724203],"iteration":923,"passed_time":4.922972604,"remaining_time":0.4049198246},
{"learn":[0.282337822],"iteration":924,"passed_time":4.924147202,"remaining_time":0.3992551786},
{"learn":[0.2822753691],"iteration":925,"passed_time":4.925586985,"remaining_time":0.3936214221},
{"learn":[0.2818807314],"iteration":926,"passed_time":4.926937106,"remaining_time":0.3879896534},
{"learn":[0.2814952373],"iteration":927,"passed_time":4.928148071,"remaining_time":0.3823563158},
{"learn":[0.2814224453],"iteration":928,"passed_time":4.929373914,"remaining_time":0.3767336361},
{"learn":[0.2810890238],"iteration":929,"passed_time":4.930451014,"remaining_time":0.3711092161},
{"learn":[0.280940874],"iteration":930,"passed_time":4.932067973,"remaining_time":0.3655345759},
{"learn":[0.2807932373],"iteration":931,"passed_time":4.933301777,"remaining_time":0.359940473},
{"learn":[0.2804618935],"iteration":932,"passed_time":4.934561813,"remaining_time":0.3543576007},
{"learn":[0.2801148212],"iteration":933,"passed_time":4.93580379,"remaining_time":0.3487827089},
{"learn":[0.2800375719],"iteration":934,"passed_time":4.937007522,"remaining_time":0.3432144267},
{"learn":[0.2796960012],"iteration":935,"passed_time":4.938295268,"remaining_time":0.3376612149},
{"learn":[0.2796119036],"iteration":936,"passed_time":4.939557009,"remaining_time":0.3321153592},
{"learn":[0.2794789019],"iteration":937,"passed_time":4.946461243,"remaining_time":0.326951596},
{"learn":[0.2794100334],"iteration":938,"passed_time":4.952071124,"remaining_time":0.3217000411},
{"learn":[0.2793520845],"iteration":939,"passed_time":4.953234534,"remaining_time":0.3161639064},
{"learn":[0.2792817457],"iteration":940,"passed_time":4.954417477,"remaining_time":0.3106382903},
{"learn":[0.2791221812],"iteration":941,"passed_time":4.955563705,"remaining_time":0.3051196336},
{"learn":[0.2789221225],"iteration":942,"passed_time":4.959318205,"remaining_time":0.2997679085},
{"learn":[0.2787652059],"iteration":943,"passed_time":4.96062014,"remaining_time":0.2942740761},
{"learn":[0.2785720271],"iteration":944,"passed_time":4.963607693,"remaining_time":0.2888872202},
{"learn":[0.278356231],"iteration":945,"passed_time":4.965635757,"remaining_time":0.2834506669},
{"learn":[0.2783022238],"iteration":946,"passed_time":4.970158232,"remaining_time":0.2781609148},
{"learn":[0.2781222645],"iteration":947,"passed_time":4.971439328,"remaining_time":0.2726949842},
{"learn":[0.2780711082],"iteration":948,"passed_time":4.9740503,"remaining_time":0.2673093417},
{"learn":[0.2777533121],"iteration":949,"passed_time":4.976189994,"remaining_time":0.2619047366},
{"learn":[0.2776783773],"iteration":950,"passed_time":5.038689369,"remaining_time":0.2596170127},
{"learn":[0.2774296472],"iteration":951,"passed_time":5.039923986,"remaining_time":0.2541138144},
{"learn":[0.2773904217],"iteration":952,"passed_time":5.045506258,"remaining_time":0.2488339917},
{"learn":[0.2773166069],"iteration":953,"passed_time":5.063009802,"remaining_time":0.2441283553},
{"learn":[0.2770144684],"iteration":954,"passed_time":5.064106308,"remaining_time":0.2386228103},
{"learn":[0.2769900253],"iteration":955,"passed_time":5.073804703,"remaining_time":0.2335223922},
{"learn":[0.2769376005],"iteration":956,"passed_time":5.079124203,"remaining_time":0.228215612},
{"learn":[0.2766905378],"iteration":957,"passed_time":5.086524586,"remaining_time":0.223000034},
{"learn":[0.2766323208],"iteration":958,"passed_time":5.103078646,"remaining_time":0.2181712456},
{"learn":[0.2765680051],"iteration":959,"passed_time":5.128446726,"remaining_time":0.2136852802},
{"learn":[0.2764104415],"iteration":960,"passed_time":5.130660249,"remaining_time":0.2082161807},
{"learn":[0.2763761883],"iteration":961,"passed_time":5.132623384,"remaining_time":0.2027439591},
{"learn":[0.2762567062],"iteration":962,"passed_time":5.162056392,"remaining_time":0.1983344616},
{"learn":[0.276185553],"iteration":963,"passed_time":5.214044101,"remaining_time":0.1947153399},
{"learn":[0.2760494156],"iteration":964,"passed_time":5.216672287,"remaining_time":0.1892057306},
{"learn":[0.2759103428],"iteration":965,"passed_time":5.244751413,"remaining_time":0.1845978758},
{"learn":[0.2756913916],"iteration":966,"passed_time":5.245899854,"remaining_time":0.1790224356},
{"learn":[0.2756501703],"iteration":967,"passed_time":5.247084424,"remaining_time":0.1734573363},
{"learn":[0.2755848412],"iteration":968,"passed_time":5.248168302,"remaining_time":0.1678980571},
{"learn":[0.2752721476],"iteration":969,"passed_time":5.26633218,"remaining_time":0.162876253},
{"learn":[0.2751435031],"iteration":970,"passed_time":5.273364682,"remaining_time":0.1574949287},
{"learn":[0.2750983855],"iteration":971,"passed_time":5.315020047,"remaining_time":0.1531075734},
{"learn":[0.2749830741],"iteration":972,"passed_time":5.31729755,"remaining_time":0.1475509084},
{"learn":[0.2749016037],"iteration":973,"passed_time":5.346368758,"remaining_time":0.1427162091},
{"learn":[0.2748471994],"iteration":974,"passed_time":5.347856406,"remaining_time":0.1371245232},
{"learn":[0.2745226126],"iteration":975,"passed_time":5.357361036,"remaining_time":0.1317383861},
{"learn":[0.2743149686],"iteration":976,"passed_time":5.387003901,"remaining_time":0.1268179015},
{"learn":[0.2741624441],"iteration":977,"passed_time":5.389147512,"remaining_time":0.1212282671},
{"learn":[0.2740997395],"iteration":978,"passed_time":5.40190526,"remaining_time":0.1158733508},
{"learn":[0.2740627095],"iteration":979,"passed_time":5.408434138,"remaining_time":0.1103762069},
{"learn":[0.2739151467],"iteration":980,"passed_time":5.441762506,"remaining_time":0.1053960118},
{"learn":[0.2738889479],"iteration":981,"passed_time":5.443810571,"remaining_time":0.09978471515},
{"learn":[0.27373422],"iteration":982,"passed_time":5.44593035,"remaining_time":0.0941819084},
{"learn":[0.2736615207],"iteration":983,"passed_time":5.469113217,"remaining_time":0.08892867019},
{"learn":[0.2735554658],"iteration":984,"passed_time":5.50554408,"remaining_time":0.08384077279},
{"learn":[0.2735289879],"iteration":985,"passed_time":5.507756953,"remaining_time":0.07820344559},
{"learn":[0.2734880115],"iteration":986,"passed_time":5.516831559,"remaining_time":0.07266343493},
{"learn":[0.2732607745],"iteration":987,"passed_time":5.518469313,"remaining_time":0.06702594307},
{"learn":[0.2732339387],"iteration":988,"passed_time":5.521692979,"remaining_time":0.06141417873},
{"learn":[0.2730449058],"iteration":989,"passed_time":5.523621905,"remaining_time":0.05579416066},
{"learn":[0.2729074099],"iteration":990,"passed_time":5.525630652,"remaining_time":0.05018231672},
{"learn":[0.2728211443],"iteration":991,"passed_time":5.579517146,"remaining_time":0.04499610601},
{"learn":[0.2725407573],"iteration":992,"passed_time":5.581775609,"remaining_time":0.03934786431},
{"learn":[0.2724237678],"iteration":993,"passed_time":5.611766221,"remaining_time":0.03387384037},
{"learn":[0.2723490905],"iteration":994,"passed_time":5.631252507,"remaining_time":0.02829775129},
{"learn":[0.2722473046],"iteration":995,"passed_time":5.652362449,"remaining_time":0.0227002508},
{"learn":[0.2720583917],"iteration":996,"passed_time":5.657072014,"remaining_time":0.01702228289},
{"learn":[0.2719749609],"iteration":997,"passed_time":5.666859317,"remaining_time":0.0113564315},
{"learn":[0.2717939173],"iteration":998,"passed_time":5.670178666,"remaining_time":0.005675854521},
{"learn":[0.271585964],"iteration":999,"passed_time":5.697876403,"remaining_time":0}
]}